Workbook
Name _Toc450375517: '6.1'!$A$2
Name _Toc450375517: '6.5'!$A$2
Name _Toc450375517: '6.6'!$A$2
Name _Toc450375517: '6.6a'!$A$2
Name _Toc450375517: '6.6b'!$A$2
Name _Toc450456886: '6.7'!$A$2
Name _Toc450456886: '6.8'!$A$2

Sheet IDX
B2: Mongolia
B3: MICS Plus
B4: 2025-26
B5: Wave 1
B7: Content
B9: Survey and sample characteristics | H9: Household energy use
B10: ='1.1a'!A1 -> Table 1.1a Response rates (after substitution, unweighted) | H10: ='5.1'!A1 -> Table 5.1 Primary reliance on clean fuels and technologies for cooking
B11: ='1.1b'!A1 -> Table 1.1b Response rates (before substitution, unweighted) | H11: ='5.2'!A1 -> Table 5.2 Primary reliance on solid fuels for cooking
B12: ='1.1.1'!A1 -> Table 1.1.1 Women response rates (unweighted) | H12: ='5.3'!A1 -> Table 5.3 Polluting fuels and technologies for cooking by place of cooking
B13: ='1.2'!A1 -> Table 1.2 Average number of call attempts (unweighted) | H13: ='5.4'!A1 -> Table 5.4 Primary reliance on clean fuels and technologies for space heating
B14: ='1.3'!A1 -> Table 1.3 Number of call attempts (unweighted) | H14: ='5.5'!A1 -> Table 5.5 Primary reliance on clean fuels and technologies for lighting
B15: ='1.4'!A1 -> Table 1.4 Duration of interviews (unweighted) | H15: ='5.6'!A1 -> Table 5.6 Primary reliance on clean fuels and technologies for cooking, space heating, and lighting
B16: ='2.1'!A1 -> Table 2.1 Housing characteristics
B17: ='2.1a'!A1 -> Table 2.1a Household and personal assets | H17: Water and sanitation
B18: ='2.1b'!A1 -> Table 2.1b Wealth quintiles | H18: ='6.1'!A1 -> Table 6.1 Use of improved and unimproved water sources
B19: ='2.2'!A1 -> Table 2.2 Household composition | H19: ='6.2'!A1 -> Table 6.2 Use of basic and limited drinking water services
B20: ='2.2a'!A1 -> Table 2.2a Background characteristics of women age 15-34 years | H20: ='6.3'!A1 -> Table 6.3 Time spent collecting water
B21: ='2.3'!A1 -> Table 2.3 Age distribution of household population by sex (5-year age groups) | H21: ='6.4'!A1 -> Table 6.4 Availability of sufficient drinking water when needed
B22: ='2.4'!A1 -> Table 2.4 Birth date reporting | H22: ='6.5'!A1 -> Table 6.5 Main reason for insufficient drinking water accessability
B23: ='3.1'!A1 -> Table 3.1 Highest education of household population age 3 years or above | H23: ='6.6'!A1 -> Table 6.6 Handwashing facility at home and availability of water and soap to wash hands when needed
B24: ='3.1a'!A1 -> Table 3.1a Education of household members age 3-24 years | H24: ='6.6a'!A1 -> Table 6.6a Main reason for insufficient water accessability to wash hands
H25: ='6.6b'!A1 -> Table 6.6b Main reason for insufficient soap accessability to wash hands
B26: Fertility and family formation | H26: ='6.7'!A1 -> Table 6.7 Use of improved and unimproved sanitation facilities
B27: ='4.1'!A1 -> Table 4.1 Fertility preferences | H27: ='6.8'!A1 -> Table 6.8 Use of basic and limited toilet facilities
B28: ='4.2'!A1 -> Table 4.2 Opinion on whether children make our lives happier and knowledge about the decreasing number of births in Mongolia
B29: ='4.3'!A1 -> Table 4.3 Attitude toward the decreasing number of births in Mongolia
B30: ='4.4'!A1 -> Table 4.4 Agreement toward the potential reasons for the low number of births in Mongolia
B31: ='4.5'!A1 -> Table 4.5 Perceived timing of first birth and ideal number of children
B32: ='4.5a'!A1 -> Table 4.5a Perceived average timing of first birth
B33: ='4.5b'!A1 -> Table 4.5b Perceived average ideal number of children
B34: ='4.6'!A1 -> Table 4.6 Perceived sufficiency of government's current measures to support childbirth and child-rearing and government measures that would influence women's decision to have children
B35: ='4.7'!A1 -> Table 4.7 Pressure or influence on personal childbearing decisions
B36: ='4.8'!A1 -> Table 4.8 Personal and social factors affecting childbearing decisions
B37: ='4.9'!A1 -> Table 4.9 Perceived timing of first marriage for a woman/man
B38: ='4.10'!A1 -> Table 4.10 Attitude toward marriage/union
B39: ='4.11'!A1 -> Table 4.11 Perceived conditions necessary for a marriage and acceptance of non-marital childbearing
B40: ='4.12'!A1 -> Table 4.12 Pressure or influence on personal decisions about marriage
B41: ='4.13'!A1 -> Table 4.13 Personal and social factors affecting decision about marriage

Sheet Preparation File
A1: # Preparation dependencies are checked by micsPlusTableR before data are read. # These dependencies install automatically with micsPlusTableR; no separate setup is needed. # micsPlusTableR supplies paths, makes these packages available to this script, # and collects hh, hl, and extra-table objects without a bootstrap script. prep_dependencies <- c( "dplyr", "haven" ) hh <- haven::read_sav(hh_path) |> arrange(HH1, HH2, HH0, HH0A) |> mutate( hhweightA = ifelse(is.na(hhweightA), 0, hhweightA), hhweightB = ifelse(is.na(hhweightB), 0, hhweightB) ) hl <- haven::read_sav(hl_path) hl <- hl |> mutate(HHID = HH0*1000000 + HH1*1000 + HH2*10 + HH0A) hh <- hh |> mutate(HHID = HH0*1000000 + HH1*1000 + HH2*10 + HH0A) hh <- hh |> mutate(total = 1) hl <- hl |> mutate(total = 1)
A2: hh_add <- hh |> select(HHID, HLnum, wm1534num, wm1534age, wm1534ed, headed, headsex, headage, headethnic, CH2) hl <- hl |> left_join(hh_add, by = "HHID")

Sheet 1.1a
A1: Table 1.1a Response rates (after substitution, unweighted) | Q1: IDX
A2: Number of households by interview results, by area of residence, region, and degree of urbanization, Mongolia MICS Plus 2025-26, Wave 1
C3: Total | D3: Area | G3: Region | M3: Degree of urbanization
D4: Urban | E4: Rural | G4: Western | H4: Khangai | I4: Central | J4: Eastern | K4: Ulaanbaatar | M4: City | N4: Town & Semi-dense area | O4: Rural area
B5: hh.sav filter(aftersub == 1) | C5: total == 1 | D5: area == 1 | E5: area == 2 | G5: region == 1 | H5: region == 2 | I5: region == 3 | J5: region == 4 | K5: region == 5 | M5: degubra == 1 | N5: degubra == 2 | O5: degubra == 3
A7: Households sampled | B7: total == 1 | C7: n_unw
A9: Interviewed | B9: HH17 %in% c(0,1)
A10: No consent for next wave | B10: HH17 == 0
A11: With consent for next wave | B11: HH17 == 1
A12: Refused | B12: HH17 %in% c(2,3)
A13: No consent for next wave | B13: HH17 == 2
A14: With consent for next wave | B14: HH17 == 3
A15: No eligible respondent | B15: HH17 == 4
A16: Phone number(s) does not belong to sampled household | B16: HH17 == 5
A17: Phone number(s) inactive | B17: HH17 == 6
A18: Respondent busy / postponed | B18: HH17 == 7
A19: No response after repeated call attempts or phone(s) turned off | B19: HH17 == 8
A20: No phone number available for sampled household | B20: HH17 == 88
A21: Other | B21: HH17 == 96
A23: Response rate | B23: HH17 %in% c(0,1) | C23: mean_unw

Sheet 1.1b
A1: Table 1.1b Response rates (before substitution, unweighted) | Q1: IDX
A2: Number of households by interview results, by area of residence, region, and degree of urbanization, Mongolia MICS Plus 2025-26, Wave 1
C3: Total | D3: Area | G3: Region | M3: Degree of urbanization
D4: Urban | E4: Rural | G4: Western | H4: Khangai | I4: Central | J4: Eastern | K4: Ulaanbaatar | M4: City | N4: Town & Semi-dense area | O4: Rural area
B5: hh.sav filter(beforesub == 1) | C5: total == 1 | D5: area == 1 | E5: area == 2 | G5: region == 1 | H5: region == 2 | I5: region == 3 | J5: region == 4 | K5: region == 5 | M5: degubra == 1 | N5: degubra == 2 | O5: degubra == 3
A7: Households sampled | B7: total == 1 | C7: n_unw
A9: Interviewed | B9: HH17 %in% c(0,1)
A10: No consent for next wave | B10: HH17 == 0
A11: With consent for next wave | B11: HH17 == 1
A12: Refused | B12: HH17 %in% c(2,3)
A13: No consent for next wave | B13: HH17 == 2
A14: With consent for next wave | B14: HH17 == 3
A15: No eligible respondent | B15: HH17 == 4
A16: Phone number(s) does not belong to sampled household | B16: HH17 == 5
A17: Phone number(s) inactive | B17: HH17 == 6
A18: Respondent busy / postponed | B18: HH17 == 7
A19: No response after repeated call attempts or phone(s) turned off | B19: HH17 == 8
A20: No phone number available for sampled household | B20: HH17 == 88
A21: Other | B21: HH17 == 96
A23: Response rate | B23: HH17 %in% c(0,1) | C23: mean_unw

Sheet 1.1.1
A1: Table 1.1.1 Women response rates (unweighted) | Q1: IDX
A2: Number of selected women age 15-34 years by interview results, by area of residence, region, and degree of urbanization, Mongolia MICS Plus 2025-26, Wave 1
C3: Total | D3: Area | G3: Region | M3: Degree of urbanization
D4: Urban | E4: Rural | G4: Western | H4: Khangai | I4: Central | J4: Eastern | K4: Ulaanbaatar | M4: City | N4: Town & Semi-dense area | O4: Rural area
B5: hh.sav filter(aftersub == 1 & RS1 != 0) | C5: total == 1 | D5: area == 1 | E5: area == 2 | G5: region == 1 | H5: region == 2 | I5: region == 3 | J5: region == 4 | K5: region == 5 | M5: degubra == 1 | N5: degubra == 2 | O5: degubra == 3
A7: Households sampled | B7: total == 1 | C7: n_unw
A9: Interviewed | B9: WHH17 %in% c(0,1)
A10: No consent for next wave | B10: WHH17 == 0
A11: With consent for next wave | B11: WHH17 == 1
A12: Refused | B12: WHH17 %in% c(2,3)
A13: No consent for next wave | B13: WHH17 == 2
A14: With consent for next wave | B14: WHH17 == 3
A15: Respondent busy / postponed | B15: WHH17 == 7
A16: No response after repeated call attempts or phone(s) turned off | B16: WHH17 == 8
A17: No adult consent for woman age 15-17 years | B17: WHH17 == 9
A19: Response rate | B19: WHH17 %in% c(0,1) | C19: mean_unw

Sheet 1.2
A1: Table 1.2 Average number of call attempts (unweighted) | Q1: IDX
A2: Average number of call attempts by interview resultsA, by area of residence, region, and degree of urbanization, Mongolia MICS Plus 2025-26, Wave 1
C3: Total | D3: Area | G3: Region | M3: Degree of urbanization
D4: Urban | E4: Rural | G4: Western | H4: Khangai | I4: Central | J4: Eastern | K4: Ulaanbaatar | M4: City | N4: Town & Semi-dense area | O4: Rural area
B5: hh.sav filter(aftersub == 1 & HH17 != 88) | C5: total == 1 | D5: area == 1 | E5: area == 2 | G5: region == 1 | H5: region == 2 | I5: region == 3 | J5: region == 4 | K5: region == 5 | M5: degubra == 1 | N5: degubra == 2 | O5: degubra == 3
A7: Total | B7: total == 1 | C7: mean_unw(CAnum)
A9: Interviewed | B9: HH17 %in% c(0,1)
A10: No consent for next wave | B10: HH17 == 0
A11: With consent for next wave | B11: HH17 == 1
A12: Refused | B12: HH17 %in% c(2,3)
A13: No consent for next wave | B13: HH17 == 2
A14: With consent for next wave | B14: HH17 == 3
A15: No eligible respondent | B15: HH17 == 4
A16: Phone number(s) does not belong to sampled household | B16: HH17 == 5
A17: Phone number(s) inactive | B17: HH17 == 6
A18: Respondent busy/postponed | B18: HH17 == 7
A19: No response after repeated call attempts or phone number(s) turned off | B19: HH17 == 8
A20: Other | B20: HH17 == 96
A21: A It does not include households with the following response codes: No phone number available for sampled household

Sheet 1.3
A1: Table 1.3 Number of call attempts (unweighted) | I1: IDX
A2: Percent and frequency distribution of households by number of call attempts and completion status of interview, Mongolia MICS Plus 2025-26, Wave 1
C3: Completed interviews | F3: Incomplete interviewsA
C4: Number | D4: Percent | F4: Number | G4: Percent
B5: hh.sav filter(aftersub == 1 & HH17 != 88) | C5: HH17 %in% c(0,1) | F5: !(HH17 %in% c(0,1))
A7: Total | B7: total == 1 | C7: n_unw | D7: p_unw(100) | F7: n_unw | G7: p_unw(100)
A9: 1 | B9: CAnum == 1
A10: 2 | B10: CAnum == 2
A11: 3 | B11: CAnum == 3
A12: 4 | B12: CAnum == 4
A13: 5 | B13: CAnum == 5
A14: 6 | B14: CAnum == 6
A15: 7 | B15: CAnum == 7
A16: 8 | B16: CAnum == 8
A17: 9 | B17: CAnum == 9
A18: 10 | B18: CAnum == 10
A19: 11 | B19: CAnum == 11
A20: 12 | B20: CAnum == 12
... A27: 19 | B27: CAnum == 19
A28: 20+ | B28: CAnum >= 20
A29: A It does not include households with the following response codes: No phone number available for sampled household

Sheet 1.4
A1: Table 1.4 Duration of interviews (unweighted) | G1: IDX
A2: Mean and median duration of interviews in minutes, Mongolia MICS Plus 2025-26, Wave 1
C3: Duration of interviews (minutes) | E3: Number of householdsA
C4: Mean | D4: Median
B5: hh.sav filter(HH17 %in% c(0,1) & intduration != 97) | C5: total == 1 | D5: total == 1 | E5: total == 1
A7: Total | B7: total == 1 | C7: mean_unw(intduration) | D7: median_unw(intduration) | E7: n_unw
A9: Area
A10: Urban | B10: area == 1
A11: Rural | B11: area == 2
A12: Degree of urbanization
A13: City | B13: degubra == 1
A14: Town & Semi-dense area | B14: degubra == 2
A15: Rural area | B15: degubra == 3
A16: Region
A17: Western | B17: region == 1
A18: Khangai | B18: region == 2
A19: Central | B19: region == 3
A20: Eastern | B20: region == 4
A21: Ulaanbaatar | B21: region == 5
A22: Sex of respondent
A23: Male | B23: respsex == 1
A24: Female | B24: respsex == 2
A25: Age of respondent
A26: <18 | B26: respage < 18
A27: 18-34 | B27: between(respage,18,34)
A28: 35-64 | B28: between(respage,35,64)
A29: 65-84 | B29: between(respage,65,84)
A30: 85+ | B30: between(respage,85,95)
A31: Education of respondent
A32: Pre-primary or none | B32: resped == 0
A33: Primary | B33: resped == 1
A34: Basic (lower secondary) | B34: resped == 2
A35: Upper secondary | B35: resped == 3
A36: Vocational | B36: resped == 4
A37: College, university | B37: resped == 5
A38: DK / Missing | B38: resped == 8
A39: Number of household members
A40: 1 | B40: HLnum == 1
A41: 2 | B41: HLnum == 2
A42: 3 | B42: HLnum == 3
A43: 4 | B43: HLnum == 4
A44: 5+ | B44: HLnum >= 5
A45: Has a woman age 15-34 years
A46: No | B46: wm1534num == 0
A47: Yes | B47: wm1534num > 0
A48: A XXX households are excluded from the calculation of mean and median durations of interview, due to interrupted calls and inconsistent information

Sheet 2.1
A1: Table 2.1 Housing characteristics | Q1: IDX
A2: Percent distribution of households by selected housing characteristics, by area of residence, region, and degree of urbanization, Mongolia MICS Plus 2025-26, Wave 1
C3: Total | D3: Area | G3: Region | M3: Degree of urbanization
D4: Urban | E4: Rural | G4: Western | H4: Khangai | I4: Central | J4: Eastern | K4: Ulaanbaatar | M4: City | N4: Town & Semi-dense area | O4: Rural area
B5: hh.sav filter(HH17 %in% c(0,1)) weight by hhweightA | C5: total == 1 | D5: area == 1 | E5: area == 2 | G5: region == 1 | H5: region == 2 | I5: region == 3 | J5: region == 4 | K5: region == 5 | M5: degubra == 1 | N5: degubra == 2 | O5: degubra == 3
A7: Total | B7: total == 1 | C7: p(100)
A9: Internet access at home
A10: Yes | B10: CH17 == 1 | CH17B == 1
A11: No | B11: (CH17 == 2 & is.na(CH17B)) | CH17B == 2
A12: DK / Missing | B12: CH17 == 9 | CH17B >= 8
A13: ElectricityA
A14: Yes | B14: CH21 == 1
A15: No | B15: CH21 == 2
A16: Missing | B16: CH21 == 9
A17: Type of accommodation
A18: Apartment, condominium | B18: CH9 == 1
A19: Convenient single-family house | B19: CH9 == 2
A20: Single-family house | B20: CH9 == 3
A21: Ger | B21: CH9 == 4
A22: Public accommodation, dormitory | B22: CH9 == 5
A23: Other | B23: CH9 == 6
A24: Missing | B24: CH9 == 9
A25: Main material of dwelling floor
A26: Natural floor (earth / sand / dung) | B26: CH25 %in% c(11,12)
A27: Rudimentary floor (wood / plank) | B27: CH25 == 21
A28: Finished floor (parquet or polished wood / laminate parquet / ceramic tiles / concrete / cement) | B28: CH25 %in% c(31,32,33,34)
A29: Other | B29: CH25 == 96
A30: Missing | B30: CH25 == 99
A31: Number of rooms
A32: 1 | B32: CH11 == 1
A33: 2 | B33: CH11 == 2
A34: 3+ | B34: between(CH11,3,96)
A35: Missing | B35: CH11 == 99
A36: Number of rooms used for sleeping
A37: 1 | B37: CH13 == 1
A38: 2 | B38: CH13 == 2
A39: 3+ | B39: between(CH13,3,96)
A40: Inconsistent / Missing | B40: CH13 >= 97
A42: Mean number of persons per room | B42: mutate(persroom = HLnum / CH11) CH11 != 99 | C42: mean(persroom)
A43: Mean number of persons per room used for sleeping | B43: mutate(perssleeproom = HLnum / CH13) CH13 < 97 | C43: mean(perssleeproom)
A45: Number of households | B45: total == 1 | C45: n
A46: A note

Sheet 2.1a
A1: Table 2.1a Household and personal assets | Q1: IDX
A2: Percentage of households by ownership of selected household and personal assets, by area of residence, region, and degree of urbanization, Mongolia MICS Plus 2025-26, Wave 1
C3: Total | D3: Area | G3: Region | M3: Degree of urbanization
D4: Urban | E4: Rural | G4: Western | H4: Khangai | I4: Central | J4: Eastern | K4: Ulaanbaatar | M4: City | N4: Town & Semi-dense area | O4: Rural area
B5: hh.sav filter(HH17 %in% c(0,1)) weight by hhweightA | C5: total == 1 | D5: area == 1 | E5: area == 2 | G5: region == 1 | H5: region == 2 | I5: region == 3 | J5: region == 4 | K5: region == 5 | M5: degubra == 1 | N5: degubra == 2 | O5: degubra == 3
A7: Percentage that own a
A8: Couch / Sofa | B8: CH20A == 1 | C8: p
A9: Metal bed | B9: CH20B == 1
A10: Refrigerator | B10: CH23B == 1
A11: Vacuum cleaner | B11: CH23D == 1
A12: Microwave oven | B12: CH23E == 1
A13: Electric oven | B13: CH23F == 1
A14: Electric iron | B14: CH23G == 1
A15: Mixer/ combine | B15: CH23H == 1
A16: Rice cooker | B16: CH23K == 1
A17: Fully automatic washing machine | B17: CH23N == 1
A18: Percentage where at least one member owns or has a
A19: Wristwatch | B19: CH24A == 1
A20: Bicycle | B20: CH24B == 1
A21: Desktop / laptop / tablet or similar computer | B21: CH14 == 1
A22: Smartphone | B22: CH16 == 1
A24: Number of households | B24: total == 1 | C24: n

Sheet 2.1b
A1: Table 2.1b Wealth quintiles | K1: IDX
A2: Percent distribution of household population, by wealth index quintile, Mongolia MICS Plus 2025-26, Wave 1
C3: Percent distribution by wealth index quintiles | H3: Total | I3: Number of household members
C4: Poorest | D4: Second | E4: Middle | F4: Fourth | G4: Richest
B5: hl.sav filter(HL7 %in% c(1,NA)) weight by hhweightA | C5: windex5 == 1 | D5: windex5 == 2 | E5: windex5 == 3 | F5: windex5 == 4 | G5: windex5 == 5 | H5: 100 | I5: total == 1
A7: Total | B7: total == 1 | C7: p | H7: 100 | I7: n
A9: Area
A10: Urban | B10: area == 1 | H10: 100
A11: Rural | B11: area == 2 | H11: 100
A12: Region
A13: Western | B13: region == 1 | H13: 100
A14: Khangai | B14: region == 2 | H14: 100
A15: Central | B15: region == 3 | H15: 100
A16: Eastern | B16: region == 4 | H16: 100
A17: Ulaanbaatar | B17: region == 5 | H17: 100
A18: Degree of urbanization
A19: City | B19: degubra == 1 | H19: 100
A20: Town & Semi-dense area | B20: degubra == 2 | H20: 100
A21: Rural area | B21: degubra == 3 | H21: 100

Sheet 2.2
A1: Table 2.2 Household composition | G1: IDX
A2: Percent and frequency distribution of households, Mongolia MICS Plus 2025-26, Wave 1
C3: Weighted percent | D3: Number of households
D4: Weighted | E4: Unweighted
B5: hh.sav filter(HH17 %in% c(0,1)) weight by hhweightA | C5: total == 1 | D5: total == 1 | E5: total == 1
A7: Total | B7: total == 1 | C7: p(100) | D7: n | E7: n_unw
A9: Area
A10: Urban | B10: area == 1
A11: Rural | B11: area == 2
A12: Region
A13: Western | B13: region == 1
A14: Khangai | B14: region == 2
A15: Central | B15: region == 3
A16: Eastern | B16: region == 4
A17: Ulaanbaatar | B17: region == 5
A18: Degree of urbanization
A19: City | B19: degubra == 1
A20: Town & Semi-dense area | B20: degubra == 2
A21: Rural area | B21: degubra == 3
A22: Sex of household head
A23: Male | B23: headsex == 1
A24: Female | B24: headsex == 2
A25: Age of household head
A26: <18 | B26: headage < 18
A27: 18-34 | B27: between(headage,18,34)
A28: 35-64 | B28: between(headage,35,64)
A29: 65-84 | B29: between(headage,65,84)
A30: 85+ | B30: between(headage,85,95)
A31: Education of household headA
A32: Pre-primary or none | B32: headed == 0
A33: Primary | B33: headed == 1
A34: Basic (lower secondary) | B34: headed == 2
A35: Upper secondary | B35: headed == 3
A36: Vocational | B36: headed == 4
A37: College, university | B37: headed == 5
A38: DK / Missing | B38: headed == 8
A39: Ethnicity of household head
A40: Khalkh | B40: CH2 == 1
A41: Khazakh | B41: CH2 == 2
A42: Durvud | B42: CH2 == 3
A43: Buriad | B43: CH2 == 4
A44: Other | B44: CH2 == 6
A45: DK / Missing | B45: CH2 >= 8
A46: Number of household members
A47: 1-2 | B47: between(HLnum,1,2)
A48: 3-4 | B48: between(HLnum,3,4)
A49: 5-6 | B49: between(HLnum,5,6)
A50: 7+ | B50: HLnum >= 7
A51: Wealth index quintile
A52: Poorest | B52: windex5 == 1
A53: Second | B53: windex5 == 2
A54: Middle | B54: windex5 == 3
A55: Fourth | B55: windex5 == 4
A56: Richest | B56: windex5 == 5
A57: Households with
A58: At least one woman age 15-34 years | B58: wm1534num > 0
A60: Mean household size | B60: total == 1 | C60: mean(HLnum)
A61: A In the tables other than 2.2 and 2.2a, the etchnicities of Khazakh, Durvud, and Buriad are combined due to small number of unweighted cases.

Sheet 2.2a
A1: Table 2.2a Background characteristics of women age 15-34 years | G1: IDX
A2: Percent and frequency distribution of women age 15-34 yearsA, Mongolia MICS Plus 2025-26, Wave 1
C3: Weighted percent | D3: Number of women age 15-34 years
D4: Weighted | E4: Unweighted
B5: hl.sav filter(HL7 %in% c(1,NA) & HL4 == 2 & between(HL6,15,34)) weight by hhweightA | C5: total == 1 | D5: total == 1 | E5: total == 1
A7: Total | B7: total == 1 | C7: p(100) | D7: n | E7: n_unw
A9: Area
A10: Urban | B10: area == 1
A11: Rural | B11: area == 2
A12: Region
A13: Western | B13: region == 1
A14: Khangai | B14: region == 2
A15: Central | B15: region == 3
A16: Eastern | B16: region == 4
A17: Ulaanbaatar | B17: region == 5
A18: Degree of urbanization
A19: City | B19: degubra == 1
A20: Town & Semi-dense area | B20: degubra == 2
A21: Rural area | B21: degubra == 3
A22: Age
A23: 15-17 | B23: between(wm1534age,15,17)
A24: 18-20 | B24: between(wm1534age,18,20)
A25: 21-24 | B25: between(wm1534age,21,24)
A26: 25-29 | B26: between(wm1534age,25,29)
A27: 30-34 | B27: between(wm1534age,30,34)
A28: Education
A29: Pre-primary or none | B29: wm1534ed == 0
A30: Primary | B30: wm1534ed == 1
A31: Basic (lower secondary) | B31: wm1534ed == 2
A32: Upper secondary | B32: wm1534ed == 3
A33: Vocational | B33: wm1534ed == 4
A34: College, university | B34: wm1534ed == 5
A35: DK / Missing | B35: wm1534ed == 8
A36: Ethnicity of household headB
A37: Khalkh | B37: CH2 == 1
A38: Khazakh | B38: CH2 == 2
A39: Durvud | B39: CH2 == 3
A40: Buriad | B40: CH2 == 4
A41: Other | B41: CH2 == 6
A42: DK / Missing | B42: CH2 >= 8
A43: Wealth index quintile
A44: Poorest | B44: windex5 == 1
A45: Second | B45: windex5 == 2
A46: Middle | B46: windex5 == 3
A47: Fourth | B47: windex5 == 4
A48: Richest | B48: windex5 == 5
A49: A In households with more than one woman age 15-34 years, one of the women is randomly selected. The sample weight for the selected woman is obtained as the multiplication of the women age 15-34 years weight with the total number of women age 15-34 years in the household. This table is based on all women age 15-34 years listed in households where interviews were completed. The age and sex distribution of women age 15-34 years in this table is not identical to those found in the rest of the tables for this age group as the findings are based on data collected on one randomly selected woman, the age and sex distribution of whom could be slightly different due to random selection.
A50: B In the tables other than 2.2 and 2.2a, the etchnicities of Khazakh, Durvud, and Buriad are combined due to small number of unweighted cases.

Sheet 2.3
A1: Table 2.3 Age distribution of household population by sex (5-year age groups) | L1: IDX
A2: Percent and frequency distribution of household population, by 5-year age groups and sex, Mongolia MICS Plus 2025-26, Wave 1
C3: Males | F3: Females | I3: Total
C4: Number | D4: Percent | F4: Number | G4: Percent | I4: Number | J4: Percent
B5: hl.sav filter(HL7 %in% c(1,NA)) weight by hhweightA | C5: HL4 == 1 | F5: HL4 == 2 | I5: total == 1
A7: Total | B7: total == 1 | C7: n | D7: p | F7: n | G7: p | I7: n | J7: p
A9: Age
A10: 0-4 | B10: between(HL6,0,4)
A11: 5-9 | B11: between(HL6,5,9)
A12: 10-14 | B12: between(HL6,10,14)
A13: 15-19 | B13: between(HL6,15,19)
A14: 20-24 | B14: between(HL6,20,24)
A15: 25-29 | B15: between(HL6,25,29)
A16: 30-34 | B16: between(HL6,30,34)
A17: 35-39 | B17: between(HL6,35,39)
A18: 40-44 | B18: between(HL6,40,44)
A19: 45-49 | B19: between(HL6,45,49)
A20: 50-54 | B20: between(HL6,50,54)
A21: 55-59 | B21: between(HL6,55,59)
... A27: 85+ | B27: between(HL6,85,95)

Sheet 2.4
A1: Table 2.4 Birth date reporting | J1: IDX
A2: Percent distribution of household population, by completeness of reporting of date of birth and ageA, Mongolia MICS Plus 2025-26, Wave 1
C3: Percent distribution by completeness of reporting of date of birth and age | G3: Total | H3: Number of household members
C4: Year and month of birth (calculated age) | D4: Reported age
D5: Year of birth only | E5: Month of birth only | F5: Neither year nor month of birth
B6: hl.sav filter(HL7 %in% c(1,NA)) weight by hhweightA | C6: HL5M < 98 & HL5Y < 9998 | D6: HL5Y < 9998 & HL5M >= 98 | E6: HL5Y >= 9998 & HL5M < 98 | F6: HL5M >= 98 & HL5Y >= 9998 | G6: 100 | H6: total == 1
A8: Total | B8: total == 1 | C8: p | G8: 100 | H8: n
A10: Area
A11: Urban | B11: area == 1 | G11: 100
A12: Rural | B12: area == 2 | G12: 100
A13: Region
A14: Western | B14: region == 1 | G14: 100
A15: Khangai | B15: region == 2 | G15: 100
A16: Central | B16: region == 3 | G16: 100
A17: Eastern | B17: region == 4 | G17: 100
A18: Ulaanbaatar | B18: region == 5 | G18: 100
A19: Degree of urbanization
A20: City | B20: degubra == 1 | G20: 100
A21: Town & Semi-dense area | B21: degubra == 2 | G21: 100
A22: Rural area | B22: degubra == 3 | G22: 100
A23: Age
A24: 0-17 | B24: between(HL6,0,17) | G24: 100
A25: 18-34 | B25: between(HL6,18,34) | G25: 100
A26: 35-64 | B26: between(HL6,35,64) | G26: 100
A27: 65-84 | B27: between(HL6,65,84) | G27: 100
A28: 85+ | B28: between(HL6,85,95) | G28: 100
A29: A In MICS Plus questionnaire, age of a household member is calculated if both year and month of birth information available and only asked if either year or month of birth information not available. Thus, for all household members, age information would be available.

Sheet 3.1
A1: Table 3.1 Highest education of household population age 3 years or above | M1: IDX
A2: Percent distribution of household members age 3 years or above by highest level of education attended, Mongolia MICS Plus 2025-26, Wave 1
C3: Percent distribution by level of highest education attended | J3: Total | K3: Number of household members age 3 years or above
C4: Pre-primary or none | D4: Primary | E4: Basic (lower secondary) | F4: Upper secondary | G4: Vocational | H4: College, university | I4: Inconsistent / DK / Missing
B5: hl.sav filter(HL7 %in% c(1,NA) & between(HL6,3,95)) weight by hhweightA | C5: edlevel == 0 | D5: edlevel == 1 | E5: edlevel == 2 | F5: edlevel == 3 | G5: edlevel == 4 | H5: edlevel == 5 | I5: edlevel == 8 | J5: 100 | K5: total == 1 | L5: total == 1
A7: Total | B7: total == 1 | C7: p | J7: 100 | K7: n | L7: n_unw
A9: Area
A10: Urban | B10: area == 1 | J10: 100
A11: Rural | B11: area == 2 | J11: 100
A12: Region
A13: Western | B13: region == 1 | J13: 100
A14: Khangai | B14: region == 2 | J14: 100
A15: Central | B15: region == 3 | J15: 100
A16: Eastern | B16: region == 4 | J16: 100
A17: Ulaanbaatar | B17: region == 5 | J17: 100
A18: Degree of urbanization
A19: City | B19: degubra == 1 | J19: 100
A20: Town & Semi-dense area | B20: degubra == 2 | J20: 100
A21: Rural area | B21: degubra == 3 | J21: 100
A22: Sex
A23: Male | B23: HL4 == 1 | J23: 100
A24: Female | B24: HL4 == 2 | J24: 100
A25: Age
A26: 3-17 | B26: between(HL6,3,17) | J26: 100
A27: 3-5 | B27: between(HL6,3,5) | J27: 100
A28: 6-10 | B28: between(HL6,6,10) | J28: 100
A29: 11-14 | B29: between(HL6,11,14) | J29: 100
A30: 15-17 | B30: between(HL6,15,17) | J30: 100
A31: 18-34 | B31: between(HL6,18,34) | J31: 100
A32: 35-64 | B32: between(HL6,35,64) | J32: 100
A33: 65-84 | B33: between(HL6,65,84) | J33: 100
A34: 85+ | B34: between(HL6,85,95) | J34: 100
A35: Ethnicity of household head
A36: Khalkh | B36: headethnic == 1 | J36: 100
A37: Khazakh, Durvud, Buriad | B37: headethnic == 2 | J37: 100
A38: Other | B38: headethnic == 6 | J38: 100
A39: DK / Missing | B39: headethnic == 8 | J39: 100
A40: Wealth index quintile
A41: Poorest | B41: windex5 == 1 | J41: 100
A42: Second | B42: windex5 == 2 | J42: 100
A43: Middle | B43: windex5 == 3 | J43: 100
A44: Fourth | B44: windex5 == 4 | J44: 100
A45: Richest | B45: windex5 == 5 | J45: 100

Sheet 3.1a
A1: Table 3.1a Education of household members age 3-24 years | Q1: IDX
A2: Percentage of household members age 3-24 years who ever attended school or any early childhood education (ECE) programme, percentage who are currently attending, and percent distribution by level of education currently attending, Mongolia MICS Plus 2025-26, Wave 1
C3: Percentage who ever attended school or any ECE programme | D3: Percentage who are currently attending school or any ECE programme | E3: Number of household members age 3-24 years | G3: Percent distribution by level of education currently attending | N3: Total | O3: Number of household members age 3-24 years who are currently attending school or any ECE programme
G4: Pre-primary or none | H4: Primary | I4: Basic (lower secondary) | J4: Upper secondary | K4: Vocational | L4: College, university | M4: Inconsistent / DK / Missing
B5: hl.sav filter(HL7 %in% c(1,NA) & between(HL6,3,24)) weight by hhweightA | C5: ED4 == 1 | D5: ED9 == 1 | E5: total == 1 | F5: total == 1 | G5: filter(ED9 == 1) - - - ED10A == 0 | H5: ED10A == 1 & ED10B <= 5 | I5: ED10A == 1 & ED10B >= 6 & ED10B <= 9 | J5: ED10A == 1 & ED10B >= 10 & ED10B < 97 | K5: ED10A == 2 | L5: ED10A == 3 | M5: ED10A >= 7 | (ED10A == 1 & ED10B >= 97) | N5: 100 | O5: total1 == 1 | P5: total1 == 1
A7: Total | B7: total == 1 | C7: p | E7: n | F7: n_unw | G7: p | N7: 100 | O7: n | P7: n_unw
A9: Area
A10: Urban | B10: area == 1 | N10: 100
A11: Rural | B11: area == 2 | N11: 100
A12: Region
A13: Western | B13: region == 1 | N13: 100
A14: Khangai | B14: region == 2 | N14: 100
A15: Central | B15: region == 3 | N15: 100
A16: Eastern | B16: region == 4 | N16: 100
A17: Ulaanbaatar | B17: region == 5 | N17: 100
A18: Degree of urbanization
A19: City | B19: degubra == 1 | N19: 100
A20: Town & Semi-dense area | B20: degubra == 2 | N20: 100
A21: Rural area | B21: degubra == 3 | N21: 100
A22: Sex
A23: Male | B23: HL4 == 1 | N23: 100
A24: Female | B24: HL4 == 2 | N24: 100
A25: Age
A26: 3-5 | B26: between(HL6,3,5) | N26: 100
A27: 6-10 | B27: between(HL6,6,10) | N27: 100
A28: 11-14 | B28: between(HL6,11,14) | N28: 100
A29: 15-17 | B29: between(HL6,15,17) | N29: 100
A30: 18-24 | B30: between(HL6,18,24) | N30: 100
A31: Education of household head
A32: Pre-primary or none | B32: headed == 0 | N32: 100
A33: Primary | B33: headed == 1 | N33: 100
A34: Basic (lower secondary) | B34: headed == 2 | N34: 100
A35: Upper secondary | B35: headed == 3 | N35: 100
A36: Vocational | B36: headed == 4 | N36: 100
A37: College, university | B37: headed == 5 | N37: 100
A38: DK / Missing | B38: headed == 8 | N38: 100
A39: Ethnicity of household head
A40: Khalkh | B40: headethnic == 1 | N40: 100
A41: Khazakh, Durvud, Buriad | B41: headethnic == 2 | N41: 100
A42: Other | B42: headethnic == 6 | N42: 100
A43: DK / Missing | B43: headethnic == 8 | N43: 100
A44: Wealth index quintile
A45: Poorest | B45: windex5 == 1 | N45: 100
A46: Second | B46: windex5 == 2 | N46: 100
A47: Middle | B47: windex5 == 3 | N47: 100
A48: Fourth | B48: windex5 == 4 | N48: 100
A49: Richest | B49: windex5 == 5 | N49: 100

Sheet 4.1
A1: Table 4.1 Fertility preferences | L1: IDX
A2: Percentage of women age 15–34 years by their preferences regarding having children, Mongolia MICS Plus 2025-26, Wave 1
C3: Percent distribution by desired number of children over the lifetime | I3: Total | J3: Number of women age 15-34 years
C4: Never wanted / doesn't want children | D4: One | E4: Two | F4: Three or more | G4: Other | H4: Missing
B5: hh.sav filter(WHH17 %in% c(0,1)) weight by wm1534weightA | C5: FP3 == 0 | D5: FP3 == 1 | E5: FP3 == 2 | F5: FP3 >= 3 & FP3 <= 20 | G5: FP3 == 96 | H5: FP3 == 99 | I5: 100 | J5: total == 1 | K5: total == 1
A7: Total | B7: total == 1 | C7: p | I7: 100 | J7: n | K7: n_unw
A9: Area
A10: Urban | B10: area == 1 | I10: 100
A11: Rural | B11: area == 2 | I11: 100
A12: Region
A13: Western | B13: region == 1 | I13: 100
A14: Khangai | B14: region == 2 | I14: 100
A15: Central | B15: region == 3 | I15: 100
A16: Eastern | B16: region == 4 | I16: 100
A17: Ulaanbaatar | B17: region == 5 | I17: 100
A18: Degree of urbanization
A19: City | B19: degubra == 1 | I19: 100
A20: Town & Semi-dense area | B20: degubra == 2 | I20: 100
A21: Rural area | B21: degubra == 3 | I21: 100
A22: Age
A23: 15-17 | B23: between(wm1534age,15,17) | I23: 100
A24: 18-20 | B24: between(wm1534age,18,20) | I24: 100
A25: 21-24 | B25: between(wm1534age,21,24) | I25: 100
A26: 25-29 | B26: between(wm1534age,25,29) | I26: 100
A27: 30-34 | B27: between(wm1534age,30,34) | I27: 100
A28: Number of births
A29: 0 | B29: FP1 == 2 | I29: 100
A30: 1 | B30: FP2 == 1 | I30: 100
A31: 2+ | B31: FP2 >= 2 & FP2 <= 20 | I31: 100
A32: Missing | B32: FP1 == 9 | I32: 100
A33: Education
A34: Pre-primary or none | B34: wm1534ed == 0 | I34: 100
A35: Primary | B35: wm1534ed == 1 | I35: 100
A36: Basic (lower secondary) | B36: wm1534ed == 2 | I36: 100
A37: Upper secondary | B37: wm1534ed == 3 | I37: 100
A38: Vocational | B38: wm1534ed == 4 | I38: 100
A39: College, university | B39: wm1534ed == 5 | I39: 100
A40: DK / Missing | B40: wm1534ed == 8 | I40: 100
A41: Marital status
A42: Ever married / in union | B42: MA1 %in% c(1,2) | MA5 %in% c(1,2) | I42: 100
A43: Never married / in union | B43: MA1 == 3 & MA5 == 3 | I43: 100
A44: Missing | B44: MA1 == 9 | MA5 == 9 | I44: 100
A45: Ethnicity of household head
A46: Khalkh | B46: headethnic == 1 | I46: 100
A47: Khazakh, Durvud, Buriad | B47: headethnic == 2 | I47: 100
A48: Other | B48: headethnic == 6 | I48: 100
A49: DK / Missing | B49: headethnic == 8 | I49: 100
A50: Wealth index quintile
A51: Poorest | B51: windex5 == 1 | I51: 100
A52: Second | B52: windex5 == 2 | I52: 100
A53: Middle | B53: windex5 == 3 | I53: 100
A54: Fourth | B54: windex5 == 4 | I54: 100
A55: Richest | B55: windex5 == 5 | I55: 100

Sheet 4.2
A1: Table 4.2 Opinion on whether children make our lives happier and knowledge about the decreasing number of births in Mongolia | M1: IDX
A2: Percent distribution of women age 15-34 years by whether agree that children make our lives happier and by whether know that the number of births in Mongolia has been decreasing in recent years, Mongolia MICS Plus 2025-26, Wave 1
C3: Percent distribution by whether agree that children make our lives happier | G3: Percent distribution by whether know about the decreasing number of births in Mongolia | K3: Number of women age 15-34 years
C4: Yes | D4: No | E4: DK / Undecided / Missing | F4: Total | G4: Yes | H4: No | I4: Missing | J4: Total
B5: hh.sav filter(WHH17 %in% c(0,1)) weight by wm1534weightA | C5: KAF1 == 1 | D5: KAF1 == 2 | E5: KAF1 %in% c(8,9) | F5: 100 | G5: KAF2 == 1 | H5: KAF2 == 2 | I5: KAF2 == 9 | J5: 100 | K5: total == 1 | L5: total == 1
A7: Total | B7: total == 1 | C7: p | F7: 100 | G7: p | J7: 100 | K7: n | L7: n_unw
A9: Area
A10: Urban | B10: area == 1 | F10: 100 | J10: 100
A11: Rural | B11: area == 2 | F11: 100 | J11: 100
A12: Region
A13: Western | B13: region == 1 | F13: 100 | J13: 100
A14: Khangai | B14: region == 2 | F14: 100 | J14: 100
A15: Central | B15: region == 3 | F15: 100 | J15: 100
A16: Eastern | B16: region == 4 | F16: 100 | J16: 100
A17: Ulaanbaatar | B17: region == 5 | F17: 100 | J17: 100
A18: Degree of urbanization
A19: City | B19: degubra == 1 | F19: 100 | J19: 100
A20: Town & Semi-dense area | B20: degubra == 2 | F20: 100 | J20: 100
A21: Rural area | B21: degubra == 3 | F21: 100 | J21: 100
A22: Age
A23: 15-17 | B23: between(wm1534age,15,17) | F23: 100 | J23: 100
A24: 18-20 | B24: between(wm1534age,18,20) | F24: 100 | J24: 100
A25: 21-24 | B25: between(wm1534age,21,24) | F25: 100 | J25: 100
A26: 25-29 | B26: between(wm1534age,25,29) | F26: 100 | J26: 100
A27: 30-34 | B27: between(wm1534age,30,34) | F27: 100 | J27: 100
A28: Number of births
A29: 0 | B29: FP1 == 2 | F29: 100 | J29: 100
A30: 1 | B30: FP2 == 1 | F30: 100 | J30: 100
A31: 2+ | B31: FP2 >= 2 & FP2 < 99 | F31: 100 | J31: 100
A32: Missing | B32: FP1 == 9 | F32: 100 | J32: 100
A33: Education
A34: Pre-primary or none | B34: wm1534ed == 0 | F34: 100 | J34: 100
A35: Primary | B35: wm1534ed == 1 | F35: 100 | J35: 100
A36: Basic (lower secondary) | B36: wm1534ed == 2 | F36: 100 | J36: 100
A37: Upper secondary | B37: wm1534ed == 3 | F37: 100 | J37: 100
A38: Vocational | B38: wm1534ed == 4 | F38: 100 | J38: 100
A39: College, university | B39: wm1534ed == 5 | F39: 100 | J39: 100
A40: DK / Missing | B40: wm1534ed == 8 | F40: 100 | J40: 100
A41: Marital status
A42: Ever married / in union | B42: MA1 %in% c(1,2) | MA5 %in% c(1,2) | F42: 100 | J42: 100
A43: Never married / in union | B43: MA1 == 3 & MA5 == 3 | F43: 100 | J43: 100
A44: Missing | B44: MA1 == 9 | MA5 == 9 | F44: 100 | J44: 100
A45: Ethnicity of household head
A46: Khalkh | B46: headethnic == 1 | F46: 100 | J46: 100
A47: Khazakh, Durvud, Buriad | B47: headethnic == 2 | F47: 100 | J47: 100
A48: Other | B48: headethnic == 6 | F48: 100 | J48: 100
A49: DK / Missing | B49: headethnic == 8 | F49: 100 | J49: 100
A50: Wealth index quintile
A51: Poorest | B51: windex5 == 1 | F51: 100 | J51: 100
A52: Second | B52: windex5 == 2 | F52: 100 | J52: 100
A53: Middle | B53: windex5 == 3 | F53: 100 | J53: 100
A54: Fourth | B54: windex5 == 4 | F54: 100 | J54: 100
A55: Richest | B55: windex5 == 5 | F55: 100 | J55: 100

Sheet 4.3
A1: Table 4.3 Attitude toward the decreasing number of births in Mongolia | T1: IDX
A2: Percent distribution of women age 15-34 years by level of perceived seriousness and level of concerns about the decreasing number of births in Mongolia, Mongolia MICS Plus 2025-26, Wave 1
C3: Percent distribution by level of perceived seriousness | J3: Percent distribution by level of concerns | R3: Number of women age 15-34 years
C4: Very serious issue | D4: Serious to a certain extent | E4: Not a serious issue | F4: Not an issue at all | G4: DK / No opinion | H4: Missing | I4: Total | J4: Extremely concerned | K4: Very concerned | L4: Moderately concerned | M4: Slightly concerned | N4: Not at all concerned | O4: DK / No opinion | P4: Missing | Q4: Total
B5: hh.sav filter(WHH17 %in% c(0,1)) weight by wm1534weightA | C5: KAF3 == 1 | D5: KAF3 == 2 | E5: KAF3 == 3 | F5: KAF3 == 4 | G5: KAF3 == 8 | H5: KAF3 == 9 | I5: 100 | J5: KAF4 == 1 | K5: KAF4 == 2 | L5: KAF4 == 3 | M5: KAF4 == 4 | N5: KAF4 == 5 | O5: KAF4 == 8 | P5: KAF4 == 9 | Q5: 100 | R5: total == 1 | S5: total == 1
A7: Total | B7: total == 1 | C7: p | I7: 100 | J7: p | Q7: 100 | R7: n | S7: n_unw
A9: Area
A10: Urban | B10: area == 1 | I10: 100 | Q10: 100
A11: Rural | B11: area == 2 | I11: 100 | Q11: 100
A12: Region
A13: Western | B13: region == 1 | I13: 100 | Q13: 100
A14: Khangai | B14: region == 2 | I14: 100 | Q14: 100
A15: Central | B15: region == 3 | I15: 100 | Q15: 100
A16: Eastern | B16: region == 4 | I16: 100 | Q16: 100
A17: Ulaanbaatar | B17: region == 5 | I17: 100 | Q17: 100
A18: Degree of urbanization
A19: City | B19: degubra == 1 | I19: 100 | Q19: 100
A20: Town & Semi-dense area | B20: degubra == 2 | I20: 100 | Q20: 100
A21: Rural area | B21: degubra == 3 | I21: 100 | Q21: 100
A22: Age
A23: 15-17 | B23: between(wm1534age,15,17) | I23: 100 | Q23: 100
A24: 18-20 | B24: between(wm1534age,18,20) | I24: 100 | Q24: 100
A25: 21-24 | B25: between(wm1534age,21,24) | I25: 100 | Q25: 100
A26: 25-29 | B26: between(wm1534age,25,29) | I26: 100 | Q26: 100
A27: 30-34 | B27: between(wm1534age,30,34) | I27: 100 | Q27: 100
A28: Number of births
A29: 0 | B29: FP1 == 2 | I29: 100 | Q29: 100
A30: 1 | B30: FP2 == 1 | I30: 100 | Q30: 100
A31: 2+ | B31: FP2 >= 2 & FP2 < 99 | I31: 100 | Q31: 100
A32: Missing | B32: FP1 == 9 | I32: 100 | Q32: 100
A33: Agree that children make our lives happier
A34: Yes | B34: KAF1 == 1 | I34: 100 | Q34: 100
A35: No | B35: KAF1 == 2 | I35: 100 | Q35: 100
A36: DK / Undecided / Missing | B36: KAF1 %in% c(8,9) | I36: 100 | Q36: 100
A37: Education
A38: Pre-primary or none | B38: wm1534ed == 0 | I38: 100 | Q38: 100
A39: Primary | B39: wm1534ed == 1 | I39: 100 | Q39: 100
A40: Basic (lower secondary) | B40: wm1534ed == 2 | I40: 100 | Q40: 100
A41: Upper secondary | B41: wm1534ed == 3 | I41: 100 | Q41: 100
A42: Vocational | B42: wm1534ed == 4 | I42: 100 | Q42: 100
A43: College, university | B43: wm1534ed == 5 | I43: 100 | Q43: 100
A44: DK / Missing | B44: wm1534ed == 8 | I44: 100 | Q44: 100
A45: Marital status
A46: Ever married / in union | B46: MA1 %in% c(1,2) | MA5 %in% c(1,2) | I46: 100 | Q46: 100
A47: Never married / in union | B47: MA1 == 3 & MA5 == 3 | I47: 100 | Q47: 100
A48: Missing | B48: MA1 == 9 | MA5 == 9 | I48: 100 | Q48: 100
A49: Ethnicity of household head
A50: Khalkh | B50: headethnic == 1 | I50: 100 | Q50: 100
A51: Khazakh, Durvud, Buriad | B51: headethnic == 2 | I51: 100 | Q51: 100
A52: Other | B52: headethnic == 6 | I52: 100 | Q52: 100
A53: DK / Missing | B53: headethnic == 8 | I53: 100 | Q53: 100
A54: Wealth index quintile
A55: Poorest | B55: windex5 == 1 | I55: 100 | Q55: 100
A56: Second | B56: windex5 == 2 | I56: 100 | Q56: 100
A57: Middle | B57: windex5 == 3 | I57: 100 | Q57: 100
A58: Fourth | B58: windex5 == 4 | I58: 100 | Q58: 100
A59: Richest | B59: windex5 == 5 | I59: 100 | Q59: 100

Sheet 4.4
A1: Table 4.4 Agreement toward the potential reasons for the low number of births in Mongolia | R1: IDX
A2: Percentage of women age 15–34 years who agree to the potential reasons for the low number of births in Mongolia, by each reason, Mongolia MICS Plus 2025-26, Wave 1
C3: Percentage who agree to the potential reasons for the low number of births in Mongolia, by reason | P3: Number of women age 15-34 years
C4: Income insecurity | D4: Focus on personal development | E4: High costs of raising children | F4: Limited access to schools and kindergartens | G4: Unsafe environment, such as air or soil pollution, for raising children | H4: Lack of confidence in child-rearing | I4: Lack of support for raising children | J4: High housing costs | K4: Too long working hours for employed people | L4: Women's reproductive health | M4: Burden of childbirth and childcare | N4: Disruption of women’s careers | O4: Other
B5: hh.sav filter(WHH17 %in% c(0,1)) weight by wm1534weightA | C5: KAF6A == 1 | D5: KAF6B == 1 | E5: KAF6C == 1 | F5: KAF6D == 1 | G5: KAF6E == 1 | H5: KAF6F == 1 | I5: KAF6G == 1 | J5: KAF6H == 1 | K5: KAF6I == 1 | L5: KAF6J == 1 | M5: KAF6K == 1 | N5: KAF6L == 1 | O5: KAF6X == 1 | P5: total == 1 | Q5: total == 1
A7: Total | B7: total == 1 | C7: p | P7: n | Q7: n_unw
A9: Area
A10: Urban | B10: area == 1
A11: Rural | B11: area == 2
A12: Region
A13: Western | B13: region == 1
A14: Khangai | B14: region == 2
A15: Central | B15: region == 3
A16: Eastern | B16: region == 4
A17: Ulaanbaatar | B17: region == 5
A18: Degree of urbanization
A19: City | B19: degubra == 1
A20: Town & Semi-dense area | B20: degubra == 2
A21: Rural area | B21: degubra == 3
A22: Age
A23: 15-17 | B23: between(wm1534age,15,17)
A24: 18-20 | B24: between(wm1534age,18,20)
A25: 21-24 | B25: between(wm1534age,21,24)
A26: 25-29 | B26: between(wm1534age,25,29)
A27: 30-34 | B27: between(wm1534age,30,34)
A28: Number of births
A29: 0 | B29: FP1 == 2
A30: 1 | B30: FP2 == 1
A31: 2+ | B31: FP2 >= 2 & FP2 < 99
A32: Missing | B32: FP1 == 9
A33: Education
A34: Pre-primary or none | B34: wm1534ed == 0
A35: Primary | B35: wm1534ed == 1
A36: Basic (lower secondary) | B36: wm1534ed == 2
A37: Upper secondary | B37: wm1534ed == 3
A38: Vocational | B38: wm1534ed == 4
A39: College, university | B39: wm1534ed == 5
A40: DK / Missing | B40: wm1534ed == 8
A41: Marital status
A42: Ever married / in union | B42: MA1 %in% c(1,2) | MA5 %in% c(1,2)
A43: Never married / in union | B43: MA1 == 3 & MA5 == 3
A44: Missing | B44: MA1 == 9 | MA5 == 9
A45: Ethnicity of household head
A46: Khalkh | B46: headethnic == 1
A47: Khazakh, Durvud, Buriad | B47: headethnic == 2
A48: Other | B48: headethnic == 6
A49: DK / Missing | B49: headethnic == 8
A50: Wealth index quintile
A51: Poorest | B51: windex5 == 1
A52: Second | B52: windex5 == 2
A53: Middle | B53: windex5 == 3
A54: Fourth | B54: windex5 == 4
A55: Richest | B55: windex5 == 5

Sheet 4.5
A1: Table 4.5 Perceived timing of first birth and ideal number of children | X1: IDX
A2: Percent distribution of women age 15-34 years by their perception on best age for women to have their first child and ideal number of children a family should have, Mongolia MICS Plus 2025-26, Wave 1
C3: Percent distribution by their perception on best age for women to have their first child | L3: Percent distribution by their perception on ideal number of children a family should have | U3: Total | V3: Number of women age 15-34 years
C4: 17-19 | D4: 20-22 | E4: 23-25 | F4: 26-28 | G4: 29-32 | H4: Other | I4: DK / No opinion | J4: Missing | K4: Total | L4: None | M4: 1 | N4: 2 | O4: 3 | P4: 4 | Q4: 5+ | R4: Other | S4: DK / No opinion | T4: Missing
B5: hh.sav filter(WHH17 %in% c(0,1)) weight by wm1534weightA | C5: between(KAF7,17,19) | D5: between(KAF7,20,22) | E5: between(KAF7,23,25) | F5: between(KAF7,26,28) | G5: between(KAF7,29,32) | H5: KAF7 == 96 | I5: KAF7 == 98 | J5: KAF7 == 99 | K5: 100 | L5: KAF8 == 0 | M5: KAF8 == 1 | N5: KAF8 == 2 | O5: KAF8 == 3 | P5: KAF8 == 4 | Q5: KAF8 >= 5 & KAF8 <= 20 | R5: KAF8 == 96 | S5: KAF8 == 98 | T5: KAF8 == 99 | U5: 100 | V5: total == 1 | W5: total == 1
A7: Total | B7: total == 1 | C7: p | K7: 100 | L7: p | U7: 100 | V7: n | W7: n_unw
A9: Area
A10: Urban | B10: area == 1 | K10: 100 | U10: 100
A11: Rural | B11: area == 2 | K11: 100 | U11: 100
A12: Region
A13: Western | B13: region == 1 | K13: 100 | U13: 100
A14: Khangai | B14: region == 2 | K14: 100 | U14: 100
A15: Central | B15: region == 3 | K15: 100 | U15: 100
A16: Eastern | B16: region == 4 | K16: 100 | U16: 100
A17: Ulaanbaatar | B17: region == 5 | K17: 100 | U17: 100
A18: Degree of urbanization
A19: City | B19: degubra == 1 | K19: 100 | U19: 100
A20: Town & Semi-dense area | B20: degubra == 2 | K20: 100 | U20: 100
A21: Rural area | B21: degubra == 3 | K21: 100 | U21: 100
A22: Age
A23: 15-17 | B23: between(wm1534age,15,17) | K23: 100 | U23: 100
A24: 18-20 | B24: between(wm1534age,18,20) | K24: 100 | U24: 100
A25: 21-24 | B25: between(wm1534age,21,24) | K25: 100 | U25: 100
A26: 25-29 | B26: between(wm1534age,25,29) | K26: 100 | U26: 100
A27: 30-34 | B27: between(wm1534age,30,34) | K27: 100 | U27: 100
A28: Number of births
A29: 0 | B29: FP1 == 2 | K29: 100 | U29: 100
A30: 1 | B30: FP2 == 1 | K30: 100 | U30: 100
A31: 2+ | B31: FP2 >= 2 & FP2 < 99 | K31: 100 | U31: 100
A32: Missing | B32: FP1 == 9 | K32: 100 | U32: 100
A33: Education
A34: Pre-primary or none | B34: wm1534ed == 0 | K34: 100 | U34: 100
A35: Primary | B35: wm1534ed == 1 | K35: 100 | U35: 100
A36: Basic (lower secondary) | B36: wm1534ed == 2 | K36: 100 | U36: 100
A37: Upper secondary | B37: wm1534ed == 3 | K37: 100 | U37: 100
A38: Vocational | B38: wm1534ed == 4 | K38: 100 | U38: 100
A39: College, university | B39: wm1534ed == 5 | K39: 100 | U39: 100
A40: DK / Missing | B40: wm1534ed == 8 | K40: 100 | U40: 100
A41: Marital status
A42: Ever married / in union | B42: MA1 %in% c(1,2) | MA5 %in% c(1,2) | K42: 100 | U42: 100
A43: Never married / in union | B43: MA1 == 3 & MA5 == 3 | K43: 100 | U43: 100
A44: Missing | B44: MA1 == 9 | MA5 == 9 | K44: 100 | U44: 100
A45: Ethnicity of household head
A46: Khalkh | B46: headethnic == 1 | K46: 100 | U46: 100
A47: Khazakh, Durvud, Buriad | B47: headethnic == 2 | K47: 100 | U47: 100
A48: Other | B48: headethnic == 6 | K48: 100 | U48: 100
A49: DK / Missing | B49: headethnic == 8 | K49: 100 | U49: 100
A50: Wealth index quintile
A51: Poorest | B51: windex5 == 1 | K51: 100 | U51: 100
A52: Second | B52: windex5 == 2 | K52: 100 | U52: 100
A53: Middle | B53: windex5 == 3 | K53: 100 | U53: 100
A54: Fourth | B54: windex5 == 4 | K54: 100 | U54: 100
A55: Richest | B55: windex5 == 5 | K55: 100 | U55: 100

Sheet 4.5a
A1: Table 4.5a Perceived average timing of first birth | F1: IDX
A2: Average best age for women to have their first birth, according to women's perception, Mongolia MICS Plus 2025-26, Wave 1
C3: Average best age for women to have their first birth, according to women's perception | D3: Number of women age 15-34 years who provided a response in years
B4: hh.sav filter(KAF7 < 96) weight by wm1534weightA | C4: total == 1 | D4: total == 1 | E4: total == 1
A6: Total | B6: total == 1 | C6: mean(KAF7) | D6: n | E6: n_unw
A8: Area
A9: Urban | B9: area == 1
A10: Rural | B10: area == 2
A11: Region
A12: Western | B12: region == 1
A13: Khangai | B13: region == 2
A14: Central | B14: region == 3
A15: Eastern | B15: region == 4
A16: Ulaanbaatar | B16: region == 5
A17: Degree of urbanization
A18: City | B18: degubra == 1
A19: Town & Semi-dense area | B19: degubra == 2
A20: Rural area | B20: degubra == 3
A21: Age
A22: 15-17 | B22: between(wm1534age,15,17)
A23: 18-20 | B23: between(wm1534age,18,20)
A24: 21-24 | B24: between(wm1534age,21,24)
A25: 25-29 | B25: between(wm1534age,25,29)
A26: 30-34 | B26: between(wm1534age,30,34)
A27: Number of births
A28: 0 | B28: FP1 == 2
A29: 1 | B29: FP2 == 1
A30: 2+ | B30: FP2 >= 2 & FP2 < 99
A31: Missing | B31: FP1 == 9
A32: Education
A33: Pre-primary or none | B33: wm1534ed == 0
A34: Primary | B34: wm1534ed == 1
A35: Basic (lower secondary) | B35: wm1534ed == 2
A36: Upper secondary | B36: wm1534ed == 3
A37: Vocational | B37: wm1534ed == 4
A38: College, university | B38: wm1534ed == 5
A39: DK / Missing | B39: wm1534ed == 8
A40: Marital status
A41: Ever married / in union | B41: MA1 %in% c(1,2) | MA5 %in% c(1,2)
A42: Never married / in union | B42: MA1 == 3 & MA5 == 3
A43: Missing | B43: MA1 == 9 | MA5 == 9
A44: Ethnicity of household head
A45: Khalkh | B45: headethnic == 1
A46: Khazakh, Durvud, Buriad | B46: headethnic == 2
A47: Other | B47: headethnic == 6
A48: DK / Missing | B48: headethnic == 8
A49: Wealth index quintile
A50: Poorest | B50: windex5 == 1
A51: Second | B51: windex5 == 2
A52: Middle | B52: windex5 == 3
A53: Fourth | B53: windex5 == 4
A54: Richest | B54: windex5 == 5

Sheet 4.5b
A1: Table 4.5b Perceived average ideal number of children | F1: IDX
A2: Average ideal number of children a family should have, according to women's perception, Mongolia MICS Plus 2025-26, Wave 1
C3: Average ideal number of children a family should have, according to women's perception | D3: Number of women age 15-34 years who provided a response in numbers
B4: hh.sav filter(KAF8 < 96) weight by wm1534weightA | C4: total == 1 | D4: total == 1 | E4: total == 1
A6: Total | B6: total == 1 | C6: mean(KAF8) | D6: n | E6: n_unw
A8: Area
A9: Urban | B9: area == 1
A10: Rural | B10: area == 2
A11: Region
A12: Western | B12: region == 1
A13: Khangai | B13: region == 2
A14: Central | B14: region == 3
A15: Eastern | B15: region == 4
A16: Ulaanbaatar | B16: region == 5
A17: Degree of urbanization
A18: City | B18: degubra == 1
A19: Town & Semi-dense area | B19: degubra == 2
A20: Rural area | B20: degubra == 3
A21: Age
A22: 15-17 | B22: between(wm1534age,15,17)
A23: 18-20 | B23: between(wm1534age,18,20)
A24: 21-24 | B24: between(wm1534age,21,24)
A25: 25-29 | B25: between(wm1534age,25,29)
A26: 30-34 | B26: between(wm1534age,30,34)
A27: Number of births
A28: 0 | B28: FP1 == 2
A29: 1 | B29: FP2 == 1
A30: 2+ | B30: FP2 >= 2 & FP2 < 99
A31: Missing | B31: FP1 == 9
A32: Education
A33: Pre-primary or none | B33: wm1534ed == 0
A34: Primary | B34: wm1534ed == 1
A35: Basic (lower secondary) | B35: wm1534ed == 2
A36: Upper secondary | B36: wm1534ed == 3
A37: Vocational | B37: wm1534ed == 4
A38: College, university | B38: wm1534ed == 5
A39: DK / Missing | B39: wm1534ed == 8
A40: Marital status
A41: Ever married / in union | B41: MA1 %in% c(1,2) | MA5 %in% c(1,2)
A42: Never married / in union | B42: MA1 == 3 & MA5 == 3
A43: Missing | B43: MA1 == 9 | MA5 == 9
A44: Ethnicity of household head
A45: Khalkh | B45: headethnic == 1
A46: Khazakh, Durvud, Buriad | B46: headethnic == 2
A47: Other | B47: headethnic == 6
A48: DK / Missing | B48: headethnic == 8
A49: Wealth index quintile
A50: Poorest | B50: windex5 == 1
A51: Second | B51: windex5 == 2
A52: Middle | B52: windex5 == 3
A53: Fourth | B53: windex5 == 4
A54: Richest | B54: windex5 == 5

Sheet 4.6
A1: Table 4.6 Perceived sufficiency of government's current measures to support childbirth and child-rearing and government measures that would influence women's decision to have children | AB1: IDX
A2: Percent distribution of women age 15-34 years by level of perceived sufficiency of government's current measures to support for childbirth and child-rearing and percentage by government measures that would influence their decision to have (more) children, Mongolia MICS Plus 2025-26, Wave 1
C3: Percent distribution by level of perceived sufficiency of government's current measures to support childbirth and child-rearing | I3: Total | J3: Percentage by government measures that would influence their decision to have (more) children | Z3: Number of women age 15-34 years
C4: More than sufficient | D4: Just sufficient | E4: Insufficient | F4: Very insufficient | G4: DK about the current government measures | H4: Missing | J4: Cash benefits during childbirth | K4: Coverage of childcare costs or provision of a nanny | L4: Housing support for raising children | M4: Three years of paid leave after childbirth | N4: Full government coverage of children’s education fees | O4: Better access to schools and kindergartens | P4: Government coverage of all fertility and child health expenses | Q4: Better access to health care services | R4: Government need to address issues of pollution and environmental safety | S4: Continue child money programme | T4: Flexible or less working hours | U4: Increasing income | V4: Improving legal environment on child rights and enhance its implementation | W4: Other | X4: Do not want any (more) children / No need for any government measures | Y4: Missing
B5: hh.sav filter(WHH17 %in% c(0,1)) weight by wm1534weightA | C5: KAF9 == 1 | D5: KAF9 == 2 | E5: KAF9 == 3 | F5: KAF9 == 4 | G5: KAF9 == 8 | H5: KAF9 == 9 | I5: 100 | J5: KAF10A == "A" | K5: KAF10B == "B" | L5: KAF10C == "C" | M5: KAF10D == "D" | N5: KAF10E == "E" | O5: KAF10F == "F" | P5: KAF10G == "G" | Q5: KAF10H == "H" | R5: KAF10I == "I" | S5: KAF10J == "J" | T5: KAF10K == "K" | U5: KAF10L == "L" | V5: KAF10M == "M" | W5: KAF10X == "X" | X5: KAF10Z == "Z" | Y5: KAF10NR == "?" | Z5: total == 1 | AA5: total == 1
A7: Total | B7: total == 1 | C7: p | I7: 100 | J7: p | Z7: n | AA7: n_unw
A9: Area
A10: Urban | B10: area == 1 | I10: 100
A11: Rural | B11: area == 2 | I11: 100
A12: Region
A13: Western | B13: region == 1 | I13: 100
A14: Khangai | B14: region == 2 | I14: 100
A15: Central | B15: region == 3 | I15: 100
A16: Eastern | B16: region == 4 | I16: 100
A17: Ulaanbaatar | B17: region == 5 | I17: 100
A18: Degree of urbanization
A19: City | B19: degubra == 1 | I19: 100
A20: Town & Semi-dense area | B20: degubra == 2 | I20: 100
A21: Rural area | B21: degubra == 3 | I21: 100
A22: Age
A23: 15-17 | B23: between(wm1534age,15,17) | I23: 100
A24: 18-20 | B24: between(wm1534age,18,20) | I24: 100
A25: 21-24 | B25: between(wm1534age,21,24) | I25: 100
A26: 25-29 | B26: between(wm1534age,25,29) | I26: 100
A27: 30-34 | B27: between(wm1534age,30,34) | I27: 100
A28: Number of births
A29: 0 | B29: FP1 == 2 | I29: 100
A30: 1 | B30: FP2 == 1 | I30: 100
A31: 2+ | B31: FP2 >= 2 & FP2 < 99 | I31: 100
A32: Missing | B32: FP1 == 9 | I32: 100
A33: Education
A34: Pre-primary or none | B34: wm1534ed == 0 | I34: 100
A35: Primary | B35: wm1534ed == 1 | I35: 100
A36: Basic (lower secondary) | B36: wm1534ed == 2 | I36: 100
A37: Upper secondary | B37: wm1534ed == 3 | I37: 100
A38: Vocational | B38: wm1534ed == 4 | I38: 100
A39: College, university | B39: wm1534ed == 5 | I39: 100
A40: DK / Missing | B40: wm1534ed == 8 | I40: 100
A41: Marital status
A42: Ever married / in union | B42: MA1 %in% c(1,2) | MA5 %in% c(1,2) | I42: 100
A43: Never married / in union | B43: MA1 == 3 & MA5 == 3 | I43: 100
A44: Missing | B44: MA1 == 9 | MA5 == 9 | I44: 100
A45: Ethnicity of household head
A46: Khalkh | B46: headethnic == 1 | I46: 100
A47: Khazakh, Durvud, Buriad | B47: headethnic == 2 | I47: 100
A48: Other | B48: headethnic == 6 | I48: 100
A49: DK / Missing | B49: headethnic == 8 | I49: 100
A50: Wealth index quintile
A51: Poorest | B51: windex5 == 1 | I51: 100
A52: Second | B52: windex5 == 2 | I52: 100
A53: Middle | B53: windex5 == 3 | I53: 100
A54: Fourth | B54: windex5 == 4 | I54: 100
A55: Richest | B55: windex5 == 5 | I55: 100

Sheet 4.7
A1: Table 4.7 Pressure or influence on personal childbearing decisions | Q1: IDX
A2: Percentage of women age 15-34 years who ever felt any pressure or influence from their family, peers, society or others regarding childbearing, percentage whose personal childbearing decisions were affected by the pressure or influence in general, and percentage by how the pressure or influence affected their personal childbearing decisions, Mongolia MICS Plus 2025-26, Wave 1
C3: Percentage who ever felt any pressure or influence from their family, peers, society or others regarding childbearing | D3: Number of women age 15-34 years | F3: Percentage whose personal childbearing decisions were affected by the pressure or influence in general | G3: Number of women age 15-34 years who ever felt any pressure or influence from their family, peers, society or others regarding childbearing | I3: Percentage by how the pressure or influence affected their personal child-bearing decisions | O3: Number of women age 15-34 years whose personal childbearing decisions were affected by the pressure or influence in general
I4: Had / planned children earlier than wanted / planned | J4: Delayed having children | K4: Changed the number of children wanted / planned children | L4: Influenced decisions about (not) continuing with a pregnancy at that time | M4: Other | N4: DK / Missing
B5: hh.sav filter(WHH17 %in% c(0,1)) weight by wm1534weightA | C5: KAF11 == 1 | D5: total == 1 | E5: total == 1 | F5: filter(KAF11 == 1) - - - KAF12 == 1 | G5: total1 == 1 | H5: total1 == 1 | I5: filter(KAF12 == 1) - - - KAF13A == "A" | J5: KAF13B == "B" | K5: KAF13C == "C" | L5: KAF13D == "D" | M5: KAF13X == "X" | N5: KAF13Z == "Z" | KAF13NR == "?" | O5: total2 == 1 | P5: total2 == 1
A7: Total | B7: total == 1 | C7: p | D7: n | E7: n_unw | F7: p | G7: n | H7: n_unw | I7: p | O7: n | P7: n_unw
A9: Area
A10: Urban | B10: area == 1
A11: Rural | B11: area == 2
A12: Region
A13: Western | B13: region == 1
A14: Khangai | B14: region == 2
A15: Central | B15: region == 3
A16: Eastern | B16: region == 4
A17: Ulaanbaatar | B17: region == 5
A18: Degree of urbanization
A19: City | B19: degubra == 1
A20: Town & Semi-dense area | B20: degubra == 2
A21: Rural area | B21: degubra == 3
A22: Age
A23: 15-17 | B23: between(wm1534age,15,17)
A24: 18-20 | B24: between(wm1534age,18,20)
A25: 21-24 | B25: between(wm1534age,21,24)
A26: 25-29 | B26: between(wm1534age,25,29)
A27: 30-34 | B27: between(wm1534age,30,34)
A28: Number of births
A29: 0 | B29: FP1 == 2
A30: 1 | B30: FP2 == 1
A31: 2+ | B31: FP2 >= 2 & FP2 < 99
A32: Missing | B32: FP1 == 9
A33: Education
A34: Pre-primary or none | B34: wm1534ed == 0
A35: Primary | B35: wm1534ed == 1
A36: Basic (lower secondary) | B36: wm1534ed == 2
A37: Upper secondary | B37: wm1534ed == 3
A38: Vocational | B38: wm1534ed == 4
A39: College, university | B39: wm1534ed == 5
A40: DK / Missing | B40: wm1534ed == 8
A41: Marital status
A42: Ever married / in union | B42: MA1 %in% c(1,2) | MA5 %in% c(1,2)
A43: Never married / in union | B43: MA1 == 3 & MA5 == 3
A44: Missing | B44: MA1 == 9 | MA5 == 9
A45: Ethnicity of household head
A46: Khalkh | B46: headethnic == 1
A47: Khazakh, Durvud, Buriad | B47: headethnic == 2
A48: Other | B48: headethnic == 6
A49: DK / Missing | B49: headethnic == 8
A50: Wealth index quintile
A51: Poorest | B51: windex5 == 1
A52: Second | B52: windex5 == 2
A53: Middle | B53: windex5 == 3
A54: Fourth | B54: windex5 == 4
A55: Richest | B55: windex5 == 5

Sheet 4.8
A1: Table 4.8 Personal and social factors affecting childbearing decisions | M1: IDX
A2: Percentage of women age 15-34 years who want (more) children by personal and social factors that would affect their decision to have (more) children, Mongolia MICS Plus 2025-26, Wave 1
C3: Percentage by personal and social factors that would affect their decision to have (more) childern | K3: Number of women age 15-34 years who want (more) children
C4: Opinions or presure from family members | D4: Opinions or presure from friends or peers | E4: Information or influence from social media and digital platforms | F4: Common societal attitudes and traditional values | G4: Personal preferences and individual values | H4: Husband / Partner’s opinion or decision | I4: Better agreement with employer or flexible working arrangements | J4: Other
B5: hh.sav filter(WHH17 %in% c(0,1) & KAF10Z != "Z") weight by wm1534weightA | C5: KAF15A == 1 | D5: KAF15B == 1 | E5: KAF15C == 1 | F5: KAF15D == 1 | G5: KAF15E == 1 | H5: KAF15F == 1 | I5: KAF15G == 1 | J5: KAF15X == 1 | K5: total == 1 | L5: total == 1
A7: Total | B7: total == 1 | C7: p | K7: n | L7: n_unw
A9: Area
A10: Urban | B10: area == 1
A11: Rural | B11: area == 2
A12: Region
A13: Western | B13: region == 1
A14: Khangai | B14: region == 2
A15: Central | B15: region == 3
A16: Eastern | B16: region == 4
A17: Ulaanbaatar | B17: region == 5
A18: Degree of urbanization
A19: City | B19: degubra == 1
A20: Town & Semi-dense area | B20: degubra == 2
A21: Rural area | B21: degubra == 3
A22: Age
A23: 15-17 | B23: between(wm1534age,15,17)
A24: 18-20 | B24: between(wm1534age,18,20)
A25: 21-24 | B25: between(wm1534age,21,24)
A26: 25-29 | B26: between(wm1534age,25,29)
A27: 30-34 | B27: between(wm1534age,30,34)
A28: Number of births
A29: 0 | B29: FP1 == 2
A30: 1 | B30: FP2 == 1
A31: 2+ | B31: FP2 >= 2 & FP2 < 99
A32: Missing | B32: FP1 == 9
A33: Education
A34: Pre-primary or none | B34: wm1534ed == 0
A35: Primary | B35: wm1534ed == 1
A36: Basic (lower secondary) | B36: wm1534ed == 2
A37: Upper secondary | B37: wm1534ed == 3
A38: Vocational | B38: wm1534ed == 4
A39: College, university | B39: wm1534ed == 5
A40: DK / Missing | B40: wm1534ed == 8
A41: Marital status
A42: Ever married / in union | B42: MA1 %in% c(1,2) | MA5 %in% c(1,2)
A43: Never married / in union | B43: MA1 == 3 & MA5 == 3
A44: Missing | B44: MA1 == 9 | MA5 == 9
A45: Ethnicity of household head
A46: Khalkh | B46: headethnic == 1
A47: Khazakh, Durvud, Buriad | B47: headethnic == 2
A48: Other | B48: headethnic == 6
A49: DK / Missing | B49: headethnic == 8
A50: Wealth index quintile
A51: Poorest | B51: windex5 == 1
A52: Second | B52: windex5 == 2
A53: Middle | B53: windex5 == 3
A54: Fourth | B54: windex5 == 4
A55: Richest | B55: windex5 == 5

Sheet 4.9
A1: Table 4.9 Perceived timing of first marriage for a woman/man | Y1: IDX
A2: Percent distribution of women age 15-34 years by their perception on best age for a woman/man to get married, Mongolia MICS Plus 2025-26, Wave 1
C3: Percent distribution by their perception on best age for a woman to get married | M3: Percent distribution by their perception on best age for a man to get married | V3: Total | W3: Number of women age 15-34 years
C4: 18-20 | D4: 21-23 | E4: 24-26 | F4: 27-29 | G4: 30-32 | H4: 34 and above | I4: Other | J4: DK / No opinion | K4: Missing | L4: Total | M4: 18-20 | N4: 21-23 | O4: 24-26 | P4: 27-29 | Q4: 30-32 | R4: 34 and above | S4: Other | T4: DK / No opinion | U4: Missing
B5: hh.sav filter(WHH17 %in% c(0,1)) weight by wm1534weightA | C5: between(MFA1B,18,20) | D5: between(MFA1B,21,23) | E5: between(MFA1B,24,26) | F5: between(MFA1B,27,29) | G5: between(MFA1B,30,32) | H5: between(MFA1B,34,70) | I5: MFA1B == 96 | J5: MFA1B == 98 | K5: MFA1B == 99 | L5: 100 | M5: between(MFA1A,18,20) | N5: between(MFA1A,21,23) | O5: between(MFA1A,24,26) | P5: between(MFA1A,27,29) | Q5: between(MFA1A,30,32) | R5: between(MFA1A,34,70) | S5: MFA1A == 96 | T5: MFA1A == 98 | U5: MFA1A == 99 | V5: 100 | W5: total == 1 | X5: total == 1
A7: Total | B7: total == 1 | C7: p | L7: 100 | M7: p | V7: 100 | W7: n | X7: n_unw
A9: Area
A10: Urban | B10: area == 1 | L10: 100 | V10: 100
A11: Rural | B11: area == 2 | L11: 100 | V11: 100
A12: Region
A13: Western | B13: region == 1 | L13: 100 | V13: 100
A14: Khangai | B14: region == 2 | L14: 100 | V14: 100
A15: Central | B15: region == 3 | L15: 100 | V15: 100
A16: Eastern | B16: region == 4 | L16: 100 | V16: 100
A17: Ulaanbaatar | B17: region == 5 | L17: 100 | V17: 100
A18: Degree of urbanization
A19: City | B19: degubra == 1 | L19: 100 | V19: 100
A20: Town & Semi-dense area | B20: degubra == 2 | L20: 100 | V20: 100
A21: Rural area | B21: degubra == 3 | L21: 100 | V21: 100
A22: Age
A23: 15-17 | B23: between(wm1534age,15,17) | L23: 100 | V23: 100
A24: 18-20 | B24: between(wm1534age,18,20) | L24: 100 | V24: 100
A25: 21-24 | B25: between(wm1534age,21,24) | L25: 100 | V25: 100
A26: 25-29 | B26: between(wm1534age,25,29) | L26: 100 | V26: 100
A27: 30-34 | B27: between(wm1534age,30,34) | L27: 100 | V27: 100
A28: Number of births
A29: 0 | B29: FP1 == 2 | L29: 100 | V29: 100
A30: 1 | B30: FP2 == 1 | L30: 100 | V30: 100
A31: 2+ | B31: FP2 >= 2 & FP2 < 99 | L31: 100 | V31: 100
A32: Missing | B32: FP1 == 9 | L32: 100 | V32: 100
A33: Education
A34: Pre-primary or none | B34: wm1534ed == 0 | L34: 100 | V34: 100
A35: Primary | B35: wm1534ed == 1 | L35: 100 | V35: 100
A36: Basic (lower secondary) | B36: wm1534ed == 2 | L36: 100 | V36: 100
A37: Upper secondary | B37: wm1534ed == 3 | L37: 100 | V37: 100
A38: Vocational | B38: wm1534ed == 4 | L38: 100 | V38: 100
A39: College, university | B39: wm1534ed == 5 | L39: 100 | V39: 100
A40: DK / Missing | B40: wm1534ed == 8 | L40: 100 | V40: 100
A41: Marital status
A42: Ever married / in union | B42: MA1 %in% c(1,2) | MA5 %in% c(1,2) | L42: 100 | V42: 100
A43: Never married / in union | B43: MA1 == 3 & MA5 == 3 | L43: 100 | V43: 100
A44: Missing | B44: MA1 == 9 | MA5 == 9 | L44: 100 | V44: 100
A45: Ethnicity of household head
A46: Khalkh | B46: headethnic == 1 | L46: 100 | V46: 100
A47: Khazakh, Durvud, Buriad | B47: headethnic == 2 | L47: 100 | V47: 100
A48: Other | B48: headethnic == 6 | L48: 100 | V48: 100
A49: DK / Missing | B49: headethnic == 8 | L49: 100 | V49: 100
A50: Wealth index quintile
A51: Poorest | B51: windex5 == 1 | L51: 100 | V51: 100
A52: Second | B52: windex5 == 2 | L52: 100 | V52: 100
A53: Middle | B53: windex5 == 3 | L53: 100 | V53: 100
A54: Fourth | B54: windex5 == 4 | L54: 100 | V54: 100
A55: Richest | B55: windex5 == 5 | L55: 100 | V55: 100

Sheet 4.9a
A1: Table 4.9a Perceived average timing of getting married | I1: IDX
A2: Average best age for women and men to get married, according to women's perception, Mongolia MICS Plus 2025-26, Wave 1
C3: The average best age for women to get married, according to women's perception | D3: Number of women age 15-34 years who provided a response in years for women's age | F3: The average best age for men to get married, according to women's perception | G3: Number of women age 15-34 years who provided a response in years for men's age
B4: hh.sav filter(WHH17 %in% c(0,1)) weight by wm1534weightA | C4: filter(MFA1B < 96) - - - MFA1B < 96 | D4: total == 1 | E4: total == 1 | F4: filter(MFA1A < 96) - - - MFA1A < 96 | G4: total == 1 | H4: total == 1
A6: Total | B6: total == 1 | C6: mean(MFA1B) | D6: n | E6: n_unw | F6: mean(MFA1A) | G6: n | H6: n_unw
A8: Area
A9: Urban | B9: area == 1
A10: Rural | B10: area == 2
A11: Region
A12: Western | B12: region == 1
A13: Khangai | B13: region == 2
A14: Central | B14: region == 3
A15: Eastern | B15: region == 4
A16: Ulaanbaatar | B16: region == 5
A17: Degree of urbanization
A18: City | B18: degubra == 1
A19: Town & Semi-dense area | B19: degubra == 2
A20: Rural area | B20: degubra == 3
A21: Age
A22: 15-17 | B22: between(wm1534age,15,17)
A23: 18-20 | B23: between(wm1534age,18,20)
A24: 21-24 | B24: between(wm1534age,21,24)
A25: 25-29 | B25: between(wm1534age,25,29)
A26: 30-34 | B26: between(wm1534age,30,34)
A27: Number of births
A28: 0 | B28: FP1 == 2
A29: 1 | B29: FP2 == 1
A30: 2+ | B30: FP2 >= 2 & FP2 < 99
A31: Missing | B31: FP1 == 9
A32: Education
A33: Pre-primary or none | B33: wm1534ed == 0
A34: Primary | B34: wm1534ed == 1
A35: Basic (lower secondary) | B35: wm1534ed == 2
A36: Upper secondary | B36: wm1534ed == 3
A37: Vocational | B37: wm1534ed == 4
A38: College, university | B38: wm1534ed == 5
A39: DK / Missing | B39: wm1534ed == 8
A40: Marital status
A41: Ever married / in union | B41: MA1 %in% c(1,2) | MA5 %in% c(1,2)
A42: Never married / in union | B42: MA1 == 3 & MA5 == 3
A43: Missing | B43: MA1 == 9 | MA5 == 9
A44: Ethnicity of household head
A45: Khalkh | B45: headethnic == 1
A46: Khazakh, Durvud, Buriad | B46: headethnic == 2
A47: Other | B47: headethnic == 6
A48: DK / Missing | B48: headethnic == 8
A49: Wealth index quintile
A50: Poorest | B50: windex5 == 1
A51: Second | B51: windex5 == 2
A52: Middle | B52: windex5 == 3
A53: Fourth | B53: windex5 == 4
A54: Richest | B54: windex5 == 5

Sheet 4.10
A1: Table 4.10 Attitude toward marriage/union | W1: IDX
A2: Percent distribution of women age 15-34 years by level of importance of official marriage in their life plans, by type of marriage or union considered important in general, and by level of acceptance of divorce, Mongolia MICS Plus 2025-26, Wave 1
C3: Percent distribution by level of importance of official marriage in their life plans | I3: Total | J3: Percent distribution by type of marriage or union considered important in general | O3: Total | P3: Percent distribution by level of acceptance of divorce | T3: Total | U3: Number of women age 15-34 years
C4: Extremely important | D4: Very important | E4: Moderately important | F4: Slightly important | G4: Not at all important | H4: DK / Missing | J4: Officially married | K4: Partner, in union | L4: Both, officially and in union | M4: None | N4: DK / Missing | P4: Acceptable | Q4: Acceptable in certain cases | R4: Not acceptable | S4: DK / Missing
B5: hh.sav filter(WHH17 %in% c(0,1)) weight by wm1534weightA | C5: MFA2 == 1 | D5: MFA2 == 2 | E5: MFA2 == 3 | F5: MFA2 == 4 | G5: MFA2 == 5 | H5: MFA2 %in% c(8,9) | I5: 100 | J5: MFA3 == 1 | K5: MFA3 == 2 | L5: MFA3 == 3 | M5: MFA3 == 4 | N5: MFA3 %in% c(8,9) | O5: 100 | P5: MFA5 == 1 | Q5: MFA5 == 2 | R5: MFA5 == 3 | S5: MFA5 %in% c(8,9) | T5: 100 | U5: total == 1 | V5: total == 1
A7: Total | B7: total == 1 | C7: p | I7: 100 | J7: p | O7: 100 | P7: p | T7: 100 | U7: n | V7: n_unw
A9: Area
A10: Urban | B10: area == 1 | I10: 100 | O10: 100 | T10: 100
A11: Rural | B11: area == 2 | I11: 100 | O11: 100 | T11: 100
A12: Region
A13: Western | B13: region == 1 | I13: 100 | O13: 100 | T13: 100
A14: Khangai | B14: region == 2 | I14: 100 | O14: 100 | T14: 100
A15: Central | B15: region == 3 | I15: 100 | O15: 100 | T15: 100
A16: Eastern | B16: region == 4 | I16: 100 | O16: 100 | T16: 100
A17: Ulaanbaatar | B17: region == 5 | I17: 100 | O17: 100 | T17: 100
A18: Degree of urbanization
A19: City | B19: degubra == 1 | I19: 100 | O19: 100 | T19: 100
A20: Town & Semi-dense area | B20: degubra == 2 | I20: 100 | O20: 100 | T20: 100
A21: Rural area | B21: degubra == 3 | I21: 100 | O21: 100 | T21: 100
A22: Age
A23: 15-17 | B23: between(wm1534age,15,17) | I23: 100 | O23: 100 | T23: 100
A24: 18-20 | B24: between(wm1534age,18,20) | I24: 100 | O24: 100 | T24: 100
A25: 21-24 | B25: between(wm1534age,21,24) | I25: 100 | O25: 100 | T25: 100
A26: 25-29 | B26: between(wm1534age,25,29) | I26: 100 | O26: 100 | T26: 100
A27: 30-34 | B27: between(wm1534age,30,34) | I27: 100 | O27: 100 | T27: 100
A28: Number of births
A29: 0 | B29: FP1 == 2 | I29: 100 | O29: 100 | T29: 100
A30: 1 | B30: FP2 == 1 | I30: 100 | O30: 100 | T30: 100
A31: 2+ | B31: FP2 >= 2 & FP2 < 99 | I31: 100 | O31: 100 | T31: 100
A32: Missing | B32: FP1 == 9 | I32: 100 | O32: 100 | T32: 100
A33: Education
A34: Pre-primary or none | B34: wm1534ed == 0 | I34: 100 | O34: 100 | T34: 100
A35: Primary | B35: wm1534ed == 1 | I35: 100 | O35: 100 | T35: 100
A36: Basic (lower secondary) | B36: wm1534ed == 2 | I36: 100 | O36: 100 | T36: 100
A37: Upper secondary | B37: wm1534ed == 3 | I37: 100 | O37: 100 | T37: 100
A38: Vocational | B38: wm1534ed == 4 | I38: 100 | O38: 100 | T38: 100
A39: College, university | B39: wm1534ed == 5 | I39: 100 | O39: 100 | T39: 100
A40: DK / Missing | B40: wm1534ed == 8 | I40: 100 | O40: 100 | T40: 100
A41: Marital status
A42: Ever married / in union | B42: MA1 %in% c(1,2) | MA5 %in% c(1,2) | I42: 100 | O42: 100 | T42: 100
A43: Never married / in union | B43: MA1 == 3 & MA5 == 3 | I43: 100 | O43: 100 | T43: 100
A44: Missing | B44: MA1 == 9 | MA5 == 9 | I44: 100 | O44: 100 | T44: 100
A45: Ethnicity of household head
A46: Khalkh | B46: headethnic == 1 | I46: 100 | O46: 100 | T46: 100
A47: Khazakh, Durvud, Buriad | B47: headethnic == 2 | I47: 100 | O47: 100 | T47: 100
A48: Other | B48: headethnic == 6 | I48: 100 | O48: 100 | T48: 100
A49: DK / Missing | B49: headethnic == 8 | I49: 100 | O49: 100 | T49: 100
A50: Wealth index quintile
A51: Poorest | B51: windex5 == 1 | I51: 100 | O51: 100 | T51: 100
A52: Second | B52: windex5 == 2 | I52: 100 | O52: 100 | T52: 100
A53: Middle | B53: windex5 == 3 | I53: 100 | O53: 100 | T53: 100
A54: Fourth | B54: windex5 == 4 | I54: 100 | O54: 100 | T54: 100
A55: Richest | B55: windex5 == 5 | I55: 100 | O55: 100 | T55: 100

Sheet 4.11
A1: Table 4.11 Perceived conditions necessary for a marriage and acceptance of non-marital childbearing | V1: IDX
A2: Percentage of women age 15-34 years by perceived conditions that must be fulfilled for a person to get married, and percent distribution by level of acceptance of non-marital childbearing, Mongolia MICS Plus 2025-26, Wave 1
C3: Percentage by perceived conditions that must be fulfilled for a person to get married | O3: Percent distribution by level of acceptance of non-marital childbearing | S3: Total | T3: Number of women age 15-34 years
C4: Economic stability | D4: Educational attainment | E4: Stable employment | F4: Having housing | G4: Parental consent | H4: Partner's proposal | I4: Pregnancy | J4: Get to know each other and family | K4: Being healthy | L4: Other | M4: Missing | O4: Acceptable | P4: Acceptable in certain cases | Q4: Not acceptable | R4: DK / Missing
B5: hh.sav filter(WHH17 %in% c(0,1)) weight by wm1534weightA | C5: MFA4A == "A" | D5: MFA4B == "B" | E5: MFA4C == "C" | F5: MFA4D == "D" | G5: MFA4E == "E" | H5: MFA4F == "F" | I5: MFA4G == "G" | J5: MFA4H == "H" | K5: MFA4I == "I" | L5: MFA4X == "X" | M5: MFA4NR == "?" | O5: MFA6 == 1 | P5: MFA6 == 2 | Q5: MFA6 == 3 | R5: MFA6 %in% c(8,9) | S5: 100 | T5: total == 1 | U5: total == 1
A7: Total | B7: total == 1 | C7: p | S7: 100 | T7: n | U7: n_unw
A9: Area
A10: Urban | B10: area == 1 | S10: 100
A11: Rural | B11: area == 2 | S11: 100
A12: Region
A13: Western | B13: region == 1 | S13: 100
A14: Khangai | B14: region == 2 | S14: 100
A15: Central | B15: region == 3 | S15: 100
A16: Eastern | B16: region == 4 | S16: 100
A17: Ulaanbaatar | B17: region == 5 | S17: 100
A18: Degree of urbanization
A19: City | B19: degubra == 1 | S19: 100
A20: Town & Semi-dense area | B20: degubra == 2 | S20: 100
A21: Rural area | B21: degubra == 3 | S21: 100
A22: Age
A23: 15-17 | B23: between(wm1534age,15,17) | S23: 100
A24: 18-20 | B24: between(wm1534age,18,20) | S24: 100
A25: 21-24 | B25: between(wm1534age,21,24) | S25: 100
A26: 25-29 | B26: between(wm1534age,25,29) | S26: 100
A27: 30-34 | B27: between(wm1534age,30,34) | S27: 100
A28: Number of births
A29: 0 | B29: FP1 == 2 | S29: 100
A30: 1 | B30: FP2 == 1 | S30: 100
A31: 2+ | B31: FP2 >= 2 & FP2 < 99 | S31: 100
A32: Missing | B32: FP1 == 9 | S32: 100
A33: Education
A34: Pre-primary or none | B34: wm1534ed == 0 | S34: 100
A35: Primary | B35: wm1534ed == 1 | S35: 100
A36: Basic (lower secondary) | B36: wm1534ed == 2 | S36: 100
A37: Upper secondary | B37: wm1534ed == 3 | S37: 100
A38: Vocational | B38: wm1534ed == 4 | S38: 100
A39: College, university | B39: wm1534ed == 5 | S39: 100
A40: DK / Missing | B40: wm1534ed == 8 | S40: 100
A41: Marital status
A42: Ever married / in union | B42: MA1 %in% c(1,2) | MA5 %in% c(1,2) | S42: 100
A43: Never married / in union | B43: MA1 == 3 & MA5 == 3 | S43: 100
A44: Missing | B44: MA1 == 9 | MA5 == 9 | S44: 100
A45: Ethnicity of household head
A46: Khalkh | B46: headethnic == 1 | S46: 100
A47: Khazakh, Durvud, Buriad | B47: headethnic == 2 | S47: 100
A48: Other | B48: headethnic == 6 | S48: 100
A49: DK / Missing | B49: headethnic == 8 | S49: 100
A50: Wealth index quintile
A51: Poorest | B51: windex5 == 1 | S51: 100
A52: Second | B52: windex5 == 2 | S52: 100
A53: Middle | B53: windex5 == 3 | S53: 100
A54: Fourth | B54: windex5 == 4 | S54: 100
A55: Richest | B55: windex5 == 5 | S55: 100

Sheet 4.12
A1: Table 4.12 Pressure or influence on personal decisions about marriage | U1: IDX
A2: Percentage of women age 15-34 years who ever felt any pressure or influence from their family, peers, society or others regarding marriage, percentage whose personal decisions about marriage were affected by the pressure or influence, and percentage by how the pressure or influence affected their personal decisions about marriage, Mongolia MICS Plus 2025-26, Wave 1
C3: Percentage who ever felt any pressure or influence from their family, peers, society or others regarding marriage | D3: Number of women age 15-34 years | F3: Percentage whose personal decisions about marriage were affected by the pressure or influence | G3: Number of women age 15-34 years who ever felt any pressure or influence from their family, peers, society or others regarding marriage | I3: Percent distribution by how the pressure or influence affected their personal decisions about marriage | R3: Total | S3: Number of women age 15-34 years whose personal decisions about marriage were affected by the pressure or influence
I4: Got married | J4: Got married earlier than palnned | K4: Stay married | L4: Did not get married / postponed | M4: Divorced / separated | N4: Living together | O4: Got boyfriend / girlfriend | P4: Other | Q4: Missing
B5: hh.sav filter(WHH17 %in% c(0,1)) weight by wm1534weightA | C5: MFA7 == 1 | D5: total == 1 | E5: total == 1 | F5: filter(MFA7 == 1) - - - MFA8 == 1 | G5: total1 == 1 | H5: total1 == 1 | I5: filter(MFA8 == 1) - - - MFA9 == 1 | J5: MFA9 == 2 | K5: MFA9 == 3 | L5: MFA9 == 4 | M5: MFA9 == 5 | N5: MFA9 == 6 | O5: MFA9 == 7 | P5: MFA9 == 96 | Q5: MFA9 == 99 | R5: 100 | S5: total2 == 1 | T5: total2 == 1
A7: Total | B7: total == 1 | C7: p | D7: n | E7: n_unw | F7: p | G7: n | H7: n_unw | I7: p | R7: 100 | S7: n | T7: n_unw
A9: Area
A10: Urban | B10: area == 1 | R10: 100
A11: Rural | B11: area == 2 | R11: 100
A12: Region
A13: Western | B13: region == 1 | R13: 100
A14: Khangai | B14: region == 2 | R14: 100
A15: Central | B15: region == 3 | R15: 100
A16: Eastern | B16: region == 4 | R16: 100
A17: Ulaanbaatar | B17: region == 5 | R17: 100
A18: Degree of urbanization
A19: City | B19: degubra == 1 | R19: 100
A20: Town & Semi-dense area | B20: degubra == 2 | R20: 100
A21: Rural area | B21: degubra == 3 | R21: 100
A22: Age
A23: 15-17 | B23: between(wm1534age,15,17) | R23: 100
A24: 18-20 | B24: between(wm1534age,18,20) | R24: 100
A25: 21-24 | B25: between(wm1534age,21,24) | R25: 100
A26: 25-29 | B26: between(wm1534age,25,29) | R26: 100
A27: 30-34 | B27: between(wm1534age,30,34) | R27: 100
A28: Number of births
A29: 0 | B29: FP1 == 2 | R29: 100
A30: 1 | B30: FP2 == 1 | R30: 100
A31: 2+ | B31: FP2 >= 2 & FP2 < 99 | R31: 100
A32: Missing | B32: FP1 == 9 | R32: 100
A33: Education
A34: Pre-primary or none | B34: wm1534ed == 0 | R34: 100
A35: Primary | B35: wm1534ed == 1 | R35: 100
A36: Basic (lower secondary) | B36: wm1534ed == 2 | R36: 100
A37: Upper secondary | B37: wm1534ed == 3 | R37: 100
A38: Vocational | B38: wm1534ed == 4 | R38: 100
A39: College, university | B39: wm1534ed == 5 | R39: 100
A40: DK / Missing | B40: wm1534ed == 8 | R40: 100
A41: Marital status
A42: Ever married / in union | B42: MA1 %in% c(1,2) | MA5 %in% c(1,2) | R42: 100
A43: Never married / in union | B43: MA1 == 3 & MA5 == 3 | R43: 100
A44: Missing | B44: MA1 == 9 | MA5 == 9 | R44: 100
A45: Ethnicity of household head
A46: Khalkh | B46: headethnic == 1 | R46: 100
A47: Khazakh, Durvud, Buriad | B47: headethnic == 2 | R47: 100
A48: Other | B48: headethnic == 6 | R48: 100
A49: DK / Missing | B49: headethnic == 8 | R49: 100
A50: Wealth index quintile
A51: Poorest | B51: windex5 == 1 | R51: 100
A52: Second | B52: windex5 == 2 | R52: 100
A53: Middle | B53: windex5 == 3 | R53: 100
A54: Fourth | B54: windex5 == 4 | R54: 100
A55: Richest | B55: windex5 == 5 | R55: 100

Sheet 4.13
A1: Table 4.13 Personal and social factors affecting decision about marriage | L1: IDX
A2: Percentage of women age 15-34 years by personal and social factors that affected or would affect their decision about marriage, Mongolia MICS Plus 2025-26, Wave 1
C3: Percentage by personal and social factors that affected or would affect their decision about marriage | J3: Number of women age 15-34 years
C4: Opinions or pressure from family members | D4: Opinions or pressure from friends or peers | E4: Information or influence from social media and digital platforms | F4: Common societal attitudes and traditional values | G4: Personal preferences and individual values | H4: Husband / Partner’s opinion or decision | I4: Other
B5: hh.sav filter(WHH17 %in% c(0,1)) weight by wm1534weightA | C5: MFA10A == 1 | D5: MFA10B == 1 | E5: MFA10C == 1 | F5: MFA10D == 1 | G5: MFA10E == 1 | H5: MFA10F == 1 | I5: MFA10X == 1 | J5: total == 1 | K5: total == 1
A7: Total | B7: total == 1 | C7: p | J7: n | K7: n_unw
A9: Area
A10: Urban | B10: area == 1
A11: Rural | B11: area == 2
A12: Region
A13: Western | B13: region == 1
A14: Khangai | B14: region == 2
A15: Central | B15: region == 3
A16: Eastern | B16: region == 4
A17: Ulaanbaatar | B17: region == 5
A18: Degree of urbanization
A19: City | B19: degubra == 1
A20: Town & Semi-dense area | B20: degubra == 2
A21: Rural area | B21: degubra == 3
A22: Age
A23: 15-17 | B23: between(wm1534age,15,17)
A24: 18-20 | B24: between(wm1534age,18,20)
A25: 21-24 | B25: between(wm1534age,21,24)
A26: 25-29 | B26: between(wm1534age,25,29)
A27: 30-34 | B27: between(wm1534age,30,34)
A28: Number of birth
A29: 0 | B29: FP1 == 2
A30: 1 | B30: FP2 == 1
A31: 2+ | B31: FP2 >= 2 & FP2 < 99
A32: Missing | B32: FP1 == 9
A33: Education
A34: Pre-primary or none | B34: wm1534ed == 0
A35: Primary | B35: wm1534ed == 1
A36: Basic (lower secondary) | B36: wm1534ed == 2
A37: Upper secondary | B37: wm1534ed == 3
A38: Vocational | B38: wm1534ed == 4
A39: College, university | B39: wm1534ed == 5
A40: DK / Missing | B40: wm1534ed == 8
A41: Marital status
A42: Ever married / in union | B42: MA1 %in% c(1,2) | MA5 %in% c(1,2)
A43: Never married / in union | B43: MA1 == 3 & MA5 == 3
A44: Missing | B44: MA1 == 9 | MA5 == 9
A45: Ethnicity of household head
A46: Khalkh | B46: headethnic == 1
A47: Khazakh, Durvud, Buriad | B47: headethnic == 2
A48: Other | B48: headethnic == 6
A49: DK / Missing | B49: headethnic == 8
A50: Wealth index quintile
A51: Poorest | B51: windex5 == 1
A52: Second | B52: windex5 == 2
A53: Middle | B53: windex5 == 3
A54: Fourth | B54: windex5 == 4
A55: Richest | B55: windex5 == 5

Sheet 5.1
A1: Table 5.1 Primary reliance on clean fuels and technologies for cooking | S1: IDX
A2: Percent distribution of household members by type of cookstove mainly used for cooking in households and percentage living in households (that reported cooking) using clean fuels and technologies for cooking, Mongolia MICS Plus 2025-26, Wave 1
C3: Percent distibution of household members living in households with primary reliance on: | M3: Total | N3: Number of household members | P3: Percentage living in households (that reported cooking) using clean fuels and technologies for cooking | Q3: Number of household members (living in households that reported cooking)
C4: Clean fuels and technologies for cooking and using: | F4: Other fuels for cooking and using: | K4: No food cooked in household | L4: Missing
C5: Electric stove | D5: Liquefied Petroleum Gas (LPG) / Cooking gas stove | F5: Manufactured solid fuel stove | G5: Traditional solid fuel stove (Non-manufactured) | H5: Liquid fuel stove | I5: Three stone stove / Open fire | J5: Other cookstove
B6: hh.sav mutate(hhmemwt = hhweightA*HLnum) filter(HH17 %in% c(0,1)) weight by hhmemwt | C6: EU1 == 2 | D6: EU1 == 5 | F6: EU1 == 6 | G6: EU1 == 7 | H6: EU1 == 8 | I6: EU1 == 10 | J6: EU1 == 96 | K6: EU1 == 97 | L6: EU1 == 99 | M6: 100 | N6: total == 1 | O6: totalHL == 1 | P6: filter(EU1 != 97) - - - EU1 %in% c(2,5) | Q6: total1 == 1 | R6: totalHL1 == 1
A8: Total | B8: total == 1 | C8: p | M8: 100 | N8: n | O8: n_unw | P8: p | Q8: n | R8: n_unw
A10: Area
A11: Urban | B11: area == 1 | M11: 100
A12: Rural | B12: area == 2 | M12: 100
A13: Region
A14: Western | B14: region == 1 | M14: 100
A15: Khangai | B15: region == 2 | M15: 100
A16: Central | B16: region == 3 | M16: 100
A17: Eastern | B17: region == 4 | M17: 100
A18: Ulaanbaatar | B18: region == 5 | M18: 100
A19: Degree of urbanization
A20: City | B20: degubra == 1 | M20: 100
A21: Town & Semi-dense area | B21: degubra == 2 | M21: 100
A22: Rural area | B22: degubra == 3 | M22: 100
A23: Education of household head
A24: Pre-primary or none | B24: headed == 0 | M24: 100
A25: Primary | B25: headed == 1 | M25: 100
A26: Basic (lower secondary) | B26: headed == 2 | M26: 100
A27: Upper secondary | B27: headed == 3 | M27: 100
A28: Vocational | B28: headed == 4 | M28: 100
A29: College, university | B29: headed == 5 | M29: 100
A30: DK / Missing | B30: headed == 8 | M30: 100
A31: Ethnicity of household head
A32: Khalkh | B32: headethnic == 1 | M32: 100
A33: Khazakh, Durvud, Buriad | B33: headethnic == 2 | M33: 100
A34: Other | B34: headethnic == 6 | M34: 100
A35: DK / Missing | B35: headethnic == 8 | M35: 100
A36: Wealth index quintile
A37: Poorest | B37: windex5 == 1 | M37: 100
A38: Second | B38: windex5 == 2 | M38: 100
A39: Middle | B39: windex5 == 3 | M39: 100
A40: Fourth | B40: windex5 == 4 | M40: 100
A41: Richest | B41: windex5 == 5 | M41: 100

Sheet 5.2
A1: Table 5.2 Primary reliance on solid fuels for cooking | V1: IDX
A2: Percent distribution of household members living in households with primary reliance on clean fuels and technologies or other fuels for cooking and percentage living in households using solid fuels for cooking by type of fuel or energy used in cookstove, Mongolia MICS Plus 2025-26, Wave 1
C3: Percent distribution of household members living in households with primary reliance on: | R3: Total | S3: Percentage living in households using solid fuels and technology for cooking | T3: Number of household members
C4: Clean fuels and technologies for cooking | E4: Solid fuels for cooking | O4: Other fuels for cooking
D5: Gasoline / Diesel (Not in generator) | E5: Coal / Lignite unprocessed | F5: Coal / Lignite briquesttes / Pellets | G5: Charcoal unprocessed | H5: Charcoal briquesttes / Pellets | I5: Wood | J5: Agricultural or crop residue / Grass / Straw / Shrubs | K5: Animal dung/ Waste | L5: Processed biomass pellets / Briquesttes | M5: Woodchips | N5: Garbage / Plastic / Tire / Used motor oil | P5: No food cooked in household | Q5: Missing
B6: hh.sav mutate(hhmemwt = hhweightA*HLnum) filter(HH17 %in% c(0,1)) weight by hhmemwt | C6: EU1 %in% c(2,5) | D6: EU4 == 2 | E6: EU4 == 4 | F6: EU4 == 5 | G6: EU4 == 6 | H6: EU4 == 7 | I6: EU4 == 8 | J6: EU4 == 9 | K6: EU4 == 10 | L6: EU4 == 11 | M6: EU4 == 12 | N6: EU4 == 13 | O6: EU4 == 96 | P6: EU1 == 97 | Q6: EU1 == 99 | EU4 == 99 | R6: 100 | S6: EU1 %in% c(6,7,10,96) | T6: total == 1 | U6: totalHL == 1
A8: Total | B8: total == 1 | C8: p | R8: 100 | S8: p | T8: n | U8: n_unw
A10: Area
A11: Urban | B11: area == 1 | R11: 100
A12: Rural | B12: area == 2 | R12: 100
A13: Region
A14: Western | B14: region == 1 | R14: 100
A15: Khangai | B15: region == 2 | R15: 100
A16: Central | B16: region == 3 | R16: 100
A17: Eastern | B17: region == 4 | R17: 100
A18: Ulaanbaatar | B18: region == 5 | R18: 100
A19: Degree of urbanization
A20: City | B20: degubra == 1 | R20: 100
A21: Town & Semi-dense area | B21: degubra == 2 | R21: 100
A22: Rural area | B22: degubra == 3 | R22: 100
A23: Education of household head
A24: Pre-primary or none | B24: headed == 0 | R24: 100
A25: Primary | B25: headed == 1 | R25: 100
A26: Basic (lower secondary) | B26: headed == 2 | R26: 100
A27: Upper secondary | B27: headed == 3 | R27: 100
A28: Vocational | B28: headed == 4 | R28: 100
A29: College, university | B29: headed == 5 | R29: 100
A30: DK / Missing | B30: headed == 8 | R30: 100
A31: Ethnicity of household head
A32: Khalkh | B32: headethnic == 1 | R32: 100
A33: Khazakh, Durvud, Buriad | B33: headethnic == 2 | R33: 100
A34: Other | B34: headethnic == 6 | R34: 100
A35: DK / Missing | B35: headethnic == 8 | R35: 100
A36: Wealth index quintile
A37: Poorest | B37: windex5 == 1 | R37: 100
A38: Second | B38: windex5 == 2 | R38: 100
A39: Middle | B39: windex5 == 3 | R39: 100
A40: Fourth | B40: windex5 == 4 | R40: 100
A41: Richest | B41: windex5 == 5 | R41: 100

Sheet 5.3
A1: Table 5.3 Polluting fuels and technologies for cooking by place of cooking | N1: IDX
A2: Percentage of household members living in households with primary reliance on polluting fuels and technologies for cooking and percent distribution by place of cooking, Mongolia MICS Plus 2025-26, Wave 1
C3: Percentage living in households with primary reliance on polluting fuels and technologies for cooking | D3: Number of household members | F3: Percent distribution of household members living in households cooking with polluting fuels and technologies and: | K3: Total | L3: Number of household members living in households using polluting fuels and technologies for cooking
F4: Place of cooking is:
F5: In main house | H5: In a separate building | I5: Other | J5: Missing
F6: No separate room | G6: In a separate room
B7: hh.sav mutate(hhmemwt = hhweightA*HLnum) filter(HH17 %in% c(0,1)) weight by hhmemwt | C7: EU1 %in% c(6,7,8,10,96) | D7: total == 1 | E7: totalHL == 1 | F7: filter(EU1 %in% c(6,7,8,10,96)) - - - EU5 == 1 | G7: EU5 == 2 | H7: EU5 == 3 | I7: EU5 == 6 | J7: EU5 == 9 | K7: 100 | L7: total1 == 1 | M7: totalHL1 == 1
A9: Total | B9: total == 1 | C9: p | D9: n | E9: n_unw | F9: p | K9: 100 | L9: n | M9: n_unw
A11: Area
A12: Urban | B12: area == 1 | K12: 100
A13: Rural | B13: area == 2 | K13: 100
A14: Region
A15: Western | B15: region == 1 | K15: 100
A16: Khangai | B16: region == 2 | K16: 100
A17: Central | B17: region == 3 | K17: 100
A18: Eastern | B18: region == 4 | K18: 100
A19: Ulaanbaatar | B19: region == 5 | K19: 100
A20: Degree of urbanization
A21: City | B21: degubra == 1 | K21: 100
A22: Town & Semi-dense area | B22: degubra == 2 | K22: 100
A23: Rural area | B23: degubra == 3 | K23: 100
A24: Education of household head
A25: Pre-primary or none | B25: headed == 0 | K25: 100
A26: Primary | B26: headed == 1 | K26: 100
A27: Basic (lower secondary) | B27: headed == 2 | K27: 100
A28: Upper secondary | B28: headed == 3 | K28: 100
A29: Vocational | B29: headed == 4 | K29: 100
A30: College, university | B30: headed == 5 | K30: 100
A31: DK / Missing | B31: headed == 8 | K31: 100
A32: Ethnicity of household head
A33: Khalkh | B33: headethnic == 1 | K33: 100
A34: Khazakh, Durvud, Buriad | B34: headethnic == 2 | K34: 100
A35: Other | B35: headethnic == 6 | K35: 100
A36: DK / Missing | B36: headethnic == 8 | K36: 100
A37: Wealth index quintile
A38: Poorest | B38: windex5 == 1 | K38: 100
A39: Second | B39: windex5 == 2 | K39: 100
A40: Middle | B40: windex5 == 3 | K40: 100
A41: Fourth | B41: windex5 == 4 | K41: 100
A42: Richest | B42: windex5 == 5 | K42: 100

Sheet 5.4
A1: Table 5.4 Primary reliance on clean fuels and technologies for space heating | AB1: IDX
A2: Percent distribution of household members by type of fuel mainly used for space heating in households and percentage living in households using clean fuels and technologies for space heating, Mongolia MICS Plus 2025-26, Wave 1
D3: Percent distribution of household members living in households with primary reliance on: | V3: Total | W3: Number of household members | Y3: Percentage living in households (that reported use of space heating) using clean fuels and technologies for space heating | Z3: Number of household members (living in households that reported use of space heating)
C4: Central heatingA | D4: Clean fuels and technologies for space heatingA | G4: Polluting fuels for space heating | T4: No space heating in household | U4: Missing
D5: Electricity (Including solar panels) | E5: Liquefied petroluem gas (LPG) / Cooking gas | G5: Gasoline / Diesel (Not in generator) | H5: Coal / Lignite unprocesed | I5: Coal / Lignite briquesttes / Pellets | J5: Charcoal unprocessed | K5: Charcoal briquesttes / Pellets | L5: Wood | M5: Agricultural or crop residue / Grass / Straw / Shrubs | N5: Animal waste / Dung | O5: Processed biomass pellets / Briquesttes | P5: Woodchips | Q5: Garbage / Plastic / Tire / Old motor oil | R5: Other | S5: DK / Missing
B6: hh.sav mutate(hhmemwt = hhweightA*HLnum) filter(HH17 %in% c(0,1)) weight by hhmemwt | C6: EU6 == 1 | D6: EU6 != 1 & EU8 == 1 | E6: EU6 != 1 & EU8 == 3 | G6: EU6 != 1 & EU8 == 6 | H6: EU6 != 1 & EU8 == 8 | I6: EU6 != 1 & EU8 == 9 | J6: EU6 != 1 & EU8 == 10 | K6: EU6 != 1 & EU8 == 11 | L6: EU6 != 1 & EU8 == 12 | M6: EU6 != 1 & EU8 == 13 | N6: EU6 != 1 & EU8 == 14 | O6: EU6 != 1 & EU8 == 15 | P6: EU6 != 1 & EU8 == 16 | Q6: EU6 != 1 & EU8 == 17 | R6: EU6 != 1 & EU8 == 96 | S6: EU6 != 1 & EU8 >= 98 | T6: EU6 == 97 | U6: EU6 == 99 | V6: 100 | W6: total == 1 | X6: totalHL == 1 | Y6: filter(EU6 != 97) - - - EU6 == 1 | EU8 %in% c(1,3) | Z6: total1 == 1 | AA6: totalHL1 == 1
A8: Total | B8: total == 1 | C8: p | V8: 100 | W8: n | X8: n_unw | Y8: p | Z8: n | AA8: n_unw
A10: Area
A11: Urban | B11: area == 1 | V11: 100
A12: Rural | B12: area == 2 | V12: 100
A13: Region
A14: Western | B14: region == 1 | V14: 100
A15: Khangai | B15: region == 2 | V15: 100
A16: Central | B16: region == 3 | V16: 100
A17: Eastern | B17: region == 4 | V17: 100
A18: Ulaanbaatar | B18: region == 5 | V18: 100
A19: Degree of urbanization
A20: City | B20: degubra == 1 | V20: 100
A21: Town & Semi-dense area | B21: degubra == 2 | V21: 100
A22: Rural area | B22: degubra == 3 | V22: 100
A23: Education of household head
A24: Pre-primary or none | B24: headed == 0 | V24: 100
A25: Primary | B25: headed == 1 | V25: 100
A26: Basic (lower secondary) | B26: headed == 2 | V26: 100
A27: Upper secondary | B27: headed == 3 | V27: 100
A28: Vocational | B28: headed == 4 | V28: 100
A29: College, university | B29: headed == 5 | V29: 100
A30: DK / Missing | B30: headed == 8 | V30: 100
A31: Ethnicity of household head
A32: Khalkh | B32: headethnic == 1 | V32: 100
A33: Khazakh, Durvud, Buriad | B33: headethnic == 2 | V33: 100
A34: Other | B34: headethnic == 6 | V34: 100
A35: DK / Missing | B35: headethnic == 8 | V35: 100
A36: Wealth index quintile
A37: Poorest | B37: windex5 == 1 | V37: 100
A38: Second | B38: windex5 == 2 | V38: 100
A39: Middle | B39: windex5 == 3 | V39: 100
A40: Fourth | B40: windex5 == 4 | V40: 100
A41: Richest | B41: windex5 == 5 | V41: 100
A42: A Central heating is considered a clean technology for individual household use irrespective of fuel type

Sheet 5.5
A1: Table 5.5 Primary reliance on clean fuels and technologies for lighting | W1: IDX
A2: Percent distribution of household members by type of lighting fuel and energy mainly used for lighting in households and percentage of household members living in households using clean fuels and technologies for lighting, Mongolia MICS Plus 2025-26, Wave 1
C3: Percent distribution of household members living in households with primary reliance on: | Q3: Total | R3: Number of household members | T3: Percentage living in households (that reported use of lighting) using clean fuels and technologies for lighting | U3: Number of household members (living in households that reported use of lighting)
C4: Clean fuels and technologies for lighting | I4: Polluting fuels for lighting | N4: Other fuel for lighting | O4: No lighting in household | P4: Missing
C5: Electricity (Including solar panels) | D5: Solar-powered lantern or flashlight | E5: Rechargeable flashlight, mobile torch or lantern | F5: Battery powered flashlight, torch or lantern | G5: Liquefied Petroleum Gas (LPG) lamp | I5: Gasoline Lamp | J5: Kerosene / Paraffin lamp | K5: Oil lamp | L5: Candle | M5: Open fire
B6: hh.sav mutate(hhmemwt = hhweightA*HLnum) filter(HH17 %in% c(0,1)) weight by hhmemwt | C6: EU9 == 1 | D6: EU9 == 2 | E6: EU9 == 3 | F6: EU9 == 4 | G6: EU9 == 6 | I6: EU9 == 7 | J6: EU9 == 8 | K6: EU9 == 9 | L6: EU9 == 10 | M6: EU9 == 11 | N6: EU9 == 96 | O6: EU9 == 97 | P6: EU9 == 99 | Q6: 100 | R6: total == 1 | S6: totalHL == 1 | T6: filter(EU9 != 97) - - - EU9 %in% c(1,2,3,4,6) | U6: total1 == 1 | V6: totalHL1 == 1
A8: Total | B8: total == 1 | C8: p | Q8: 100 | R8: n | S8: n_unw | T8: p | U8: n | V8: n_unw
A10: Area
A11: Urban | B11: area == 1 | Q11: 100
A12: Rural | B12: area == 2 | Q12: 100
A13: Region
A14: Western | B14: region == 1 | Q14: 100
A15: Khangai | B15: region == 2 | Q15: 100
A16: Central | B16: region == 3 | Q16: 100
A17: Eastern | B17: region == 4 | Q17: 100
A18: Ulaanbaatar | B18: region == 5 | Q18: 100
A19: Degree of urbanization
A20: City | B20: degubra == 1 | Q20: 100
A21: Town & Semi-dense area | B21: degubra == 2 | Q21: 100
A22: Rural area | B22: degubra == 3 | Q22: 100
A23: Education of household head
A24: Pre-primary or none | B24: headed == 0 | Q24: 100
A25: Primary | B25: headed == 1 | Q25: 100
A26: Basic (lower secondary) | B26: headed == 2 | Q26: 100
A27: Upper secondary | B27: headed == 3 | Q27: 100
A28: Vocational | B28: headed == 4 | Q28: 100
A29: College, university | B29: headed == 5 | Q29: 100
A30: DK / Missing | B30: headed == 8 | Q30: 100
A31: Ethnicity of household head
A32: Khalkh | B32: headethnic == 1 | Q32: 100
A33: Khazakh, Durvud, Buriad | B33: headethnic == 2 | Q33: 100
A34: Other | B34: headethnic == 6 | Q34: 100
A35: DK / Missing | B35: headethnic == 8 | Q35: 100
A36: Wealth index quintile
A37: Poorest | B37: windex5 == 1 | Q37: 100
A38: Second | B38: windex5 == 2 | Q38: 100
A39: Middle | B39: windex5 == 3 | Q39: 100
A40: Fourth | B40: windex5 == 4 | Q40: 100
A41: Richest | B41: windex5 == 5 | Q41: 100

Sheet 5.6
A1: Table 5.6 Primary reliance on clean fuels and technologies for cooking, space heating, and lighting | F1: IDX
A2: Percentage of household members living in households using clean fuels and technologies for cooking, space heating, and lighting, Mongolia MICS Plus 2025-26, Wave 1
C3: Percentage living in households using clean fuels and technologies for cooking, space heating, and lightingA | D3: Number of household members
B4: hh.sav mutate(hhmemwt = hhweightA*HLnum) filter(HH17 %in% c(0,1)) weight by hhmemwt | C4: EU1 %in% c(2,5,97) & (EU6 == 97 | EU6 == 1 | EU8 %in% c(1,3)) & EU9 %in% c(1,2,3,4,6,97) | D4: total == 1 | E4: totalHL == 1
A6: Total | B6: total == 1 | C6: p | D6: n | E6: n_unw
A8: Area
A9: Urban | B9: area == 1
A10: Rural | B10: area == 2
A11: Region
A12: Western | B12: region == 1
A13: Khangai | B13: region == 2
A14: Central | B14: region == 3
A15: Eastern | B15: region == 4
A16: Ulaanbaatar | B16: region == 5
A17: Degree of urbanization
A18: City | B18: degubra == 1
A19: Town & Semi-dense area | B19: degubra == 2
A20: Rural area | B20: degubra == 3
A21: Education of household head
A22: Pre-primary or none | B22: headed == 0
A23: Primary | B23: headed == 1
A24: Basic (lower secondary) | B24: headed == 2
A25: Upper secondary | B25: headed == 3
A26: Vocational | B26: headed == 4
A27: College, university | B27: headed == 5
A28: DK / Missing | B28: headed == 8
A29: Ethnicity of household head
A30: Khalkh | B30: headethnic == 1
A31: Khazakh, Durvud, Buriad | B31: headethnic == 2
A32: Other | B32: headethnic == 6
A33: DK / Missing | B33: headethnic == 8
A34: Wealth index quintile
A35: Poorest | B35: windex5 == 1
A36: Second | B36: windex5 == 2
A37: Middle | B37: windex5 == 3
A38: Fourth | B38: windex5 == 4
A39: Richest | B39: windex5 == 5
A40: A For households that do not use space heating, the computation is based on reliance on clean fuel use for cooking and lighting. Similar approach is applied for households that report no cooking or do not use lighting.

Sheet 6.1
A1: Table 6.1 Use of improved and unimproved water sources | AA1: IDX
A2: Percent distribution of household members by main source of drinking water and percentage using improved sources of drinking water, Mongolia MICS Plus 2025-26, Wave 1
C3: Percent distribution of household members by main source of drinking water | W3: Total | X3: Percentage using improved sources of drinking water | Y3: Number of household members
C4: Improved drinking water sources | Q4: Unimproved drinking water sources
C5: Piped water | E5: Tube well/ Borehole | F5: Protected dug well | G5: Protected springs | H5: Rain, snow water | I5: Ice | J5: Tanker truck | K5: Cart with small tank | L5: Water kiosk | N5: Bottled water | O5: Large bottle / Dispenser refill | Q5: Unprotected dug well | R5: Unprotected springs | S5: Surface water | T5: Other | V5: Missing
C6: Into dwelling | D6: Into yard / plot | L6: Connected with piped water | M6: Not connected with piped water
B7: hh.sav mutate(hhmemwt = hhweightA*HLnum) filter(HH17 %in% c(0,1)) weight by hhmemwt | C7: WS1 == 11 | D7: WS1 == 12 | E7: WS1 == 21 | F7: WS1 == 31 | G7: WS1 == 41 | H7: WS1 == 51 | I7: WS1 == 52 | J7: WS1 == 61 | K7: WS1 == 71 | L7: WS1 == 72 | M7: WS1 == 73 | N7: WS1 == 91 | O7: WS1 == 93 | Q7: WS1 == 32 | R7: WS1 == 42 | S7: WS1 == 81 | T7: WS1 == 96 | V7: WS1 == 99 | W7: 100 | X7: WS1 %in% c(11,12,21,31,41,51,52,61,71,72,73,91,93) | Y7: total == 1 | Z7: totalHL == 1
A9: Total | B9: total == 1 | C9: p | W9: 100 | X9: p | Y9: n | Z9: n_unw
A11: Area
A12: Urban | B12: area == 1 | W12: 100
A13: Rural | B13: area == 2 | W13: 100
A14: Region
A15: Western | B15: region == 1 | W15: 100
A16: Khangai | B16: region == 2 | W16: 100
A17: Central | B17: region == 3 | W17: 100
A18: Eastern | B18: region == 4 | W18: 100
A19: Ulaanbaatar | B19: region == 5 | W19: 100
A20: Degree of urbanization
A21: City | B21: degubra == 1 | W21: 100
A22: Town & Semi-dense area | B22: degubra == 2 | W22: 100
A23: Rural area | B23: degubra == 3 | W23: 100
A24: Education of household head
A25: Pre-primary or none | B25: headed == 0 | W25: 100
A26: Primary | B26: headed == 1 | W26: 100
A27: Basic (lower secondary) | B27: headed == 2 | W27: 100
A28: Upper secondary | B28: headed == 3 | W28: 100
A29: Vocational | B29: headed == 4 | W29: 100
A30: College, university | B30: headed == 5 | W30: 100
A31: DK / Missing | B31: headed == 8 | W31: 100
A32: Ethnicity of household head
A33: Khalkh | B33: headethnic == 1 | W33: 100
A34: Khazakh, Durvud, Buriad | B34: headethnic == 2 | W34: 100
A35: Other | B35: headethnic == 6 | W35: 100
A36: DK / Missing | B36: headethnic == 8 | W36: 100
A37: Wealth index quintile
A38: Poorest | B38: windex5 == 1 | W38: 100
A39: Second | B39: windex5 == 2 | W39: 100
A40: Middle | B40: windex5 == 3 | W40: 100
A41: Fourth | B41: windex5 == 4 | W41: 100
A42: Richest | B42: windex5 == 5 | W42: 100

Sheet 6.2
A1: Table 6.2 Use of basic and limited drinking water services | R1: IDX
A2: Percent distribution of household members by time to go to source of drinking water, get water and return, for users of improved and unimproved drinking water sources and percentage using at least basic drinking water services, Mongolia MICS Plus 2025-26, Wave 1
C3: Percent distribution of household members by time to source of drinking water | N3: Total | O3: Percentage using at least basic drinking water services | P3: Number of household members
C4: Improved drinking water sources | H4: Unimproved drinking water sources | M4: Missing
C5: Water on premisesA | D5: Up to and including 30 minutes | E5: More than 30 minutes | F5: DK / Missing | H5: Water on premisesA | I5: Up to and including 30 minutes | J5: More than 30 minutes | K5: DK / Missing
B6: hh.sav mutate(hhmemwt = hhweightA*HLnum) filter(HH17 %in% c(0,1)) weight by hhmemwt | C6: WS1 %in% c(11,12,21,31,41,51,52,61,71,91,93) & (WS1 %in% c(11,12) | WS3 %in% c(1,2) | WS4 == 0) | D6: (WS1 %in% c(11,12,21,31,41,51,52,61,71,72,73,91,93) & between(WS4,1,30)) | (WS1 %in% c(72,73) & (WS1 %in% c(11,12) | WS3 %in% c(1,2) | WS4 == 0)) | E6: WS1 %in% c(11,12,21,31,41,51,52,61,71,72,73,91,93) & between(WS4,31,990) | F6: WS1 %in% c(11,12,21,31,41,51,52,61,71,72,73,91,93) & (WS3 == 9 | WS4 >= 998) | H6: WS1 %in% c(32,42,81,96) & (WS3 %in% c(1,2) | WS4 == 0) | I6: WS1 %in% c(32,42,81,96) & between(WS4,1,30) | J6: WS1 %in% c(32,42,81,96) & between(WS4,31,990) | K6: WS1 %in% c(32,42,81,96) & (WS3 == 9 | WS4 >= 998) | M6: WS1 == 99 | N6: 100 | O6: WS1 %in% c(11,12,21,31,41,51,52,61,71,72,73,91,93) & (WS1 %in% c(11,12) | WS3 %in% c(1,2) | WS4 < 31) | P6: total == 1 | Q6: totalHL == 1
A8: Total | B8: total == 1 | C8: p | N8: 100 | O8: p | P8: n | Q8: n_unw
A10: Area
A11: Urban | B11: area == 1 | N11: 100
A12: Rural | B12: area == 2 | N12: 100
A13: Region
A14: Western | B14: region == 1 | N14: 100
A15: Khangai | B15: region == 2 | N15: 100
A16: Central | B16: region == 3 | N16: 100
A17: Eastern | B17: region == 4 | N17: 100
A18: Ulaanbaatar | B18: region == 5 | N18: 100
A19: Degree of urbanization
A20: City | B20: degubra == 1 | N20: 100
A21: Town & Semi-dense area | B21: degubra == 2 | N21: 100
A22: Rural area | B22: degubra == 3 | N22: 100
A23: Education of household head
A24: Pre-primary or none | B24: headed == 0 | N24: 100
A25: Primary | B25: headed == 1 | N25: 100
A26: Basic (lower secondary) | B26: headed == 2 | N26: 100
A27: Upper secondary | B27: headed == 3 | N27: 100
A28: Vocational | B28: headed == 4 | N28: 100
A29: College, university | B29: headed == 5 | N29: 100
A30: DK / Missing | B30: headed == 8 | N30: 100
A31: Main source of drinking water
A32: Improved sources | B32: WS1 %in% c(11,12,21,31,41,51,52,61,71,72,73,91,93) | N32: 100
A33: Piped water | B33: WS1 %in% c(11,12) | N33: 100
A34: Tube well / Borehole | B34: WS1 == 21 | N34: 100
A35: Protected well or spring | B35: WS1 %in% c(31,41) | N35: 100
A36: Rain or snow water / Ice | B36: WS1 %in% c(51,52) | N36: 100
A37: Water kiosk | B37: WS1 %in% c(72,73) | N37: 100
A38: Tanker truck / Cart with small tank | B38: WS1 %in% c(61,71) | N38: 100
A39: Bottled water | B39: WS1 == 91 | N39: 100
A40: Large bottle / Dispenser refill | B40: WS1 == 93 | N40: 100
A41: Unimproved sources | B41: WS1 %in% c(32,42,81,96) | N41: 100
A42: Unprotected well or spring | B42: WS1 %in% c(32,42) | N42: 100
A43: Surface water | B43: WS1 == 81 | N43: 100
... A45: Missing | B45: WS1 == 99 | N45: 100
A46: Ethnicity of household head
A47: Khalkh | B47: headethnic == 1 | N47: 100
A48: Khazakh, Durvud, Buriad | B48: headethnic == 2 | N48: 100
A49: Other | B49: headethnic == 6 | N49: 100
A50: DK / Missing | B50: headethnic == 8 | N50: 100
A51: Wealth index quintile
A52: Poorest | B52: windex5 == 1 | N52: 100
A53: Second | B53: windex5 == 2 | N53: 100
A54: Middle | B54: windex5 == 3 | N54: 100
A55: Fourth | B55: windex5 == 4 | N55: 100
A56: Richest | B56: windex5 == 5 | N56: 100
A57: A Water on premises are water sources that are either 1) water piped into dwelling, yard, or plot, or 2) water from other sources reported to be located in the dwelling yard or plot, or 3) where household members do not collect water. This excludes water kiosk which by definition are off-premises.

Sheet 6.3
A1: Table 6.3 Time spent collecting water | N1: IDX
A2: Percent distribution of average time spent collecting water, and percentage of household members using improved water sources where the water collection takes no more than 30 minutes per trip, Mongolia MICS Plus 2025-26, Wave 1
C3: Average time spent collecting water per trip | H3: Total | I3: Number of household members without drinking water on premises where household members collect water | K3: Percentage using improved sources where the water collection takes no more than 30 minutes per trip | L3: Number of household members without drinking water on premises where household members collect water from an improved source
C4: Up to and including 30 minutes | D4: From 31 minutes to 1 hour | E4: Over 1 hour to 3 hours | F4: Over 3 hours | G4: DK / Missing
B5: hh.sav mutate(hhmemwt = hhweightA*HLnum) filter(HH17 %in% c(0,1) & WS4 != 0) weight by hhmemwt | C5: between(WS4,1,30) | D5: between(WS4,31,60) | E5: between(WS4,61,180) | F5: between(WS4,181,990) | G5: WS4 >= 998 | H5: 100 | I5: total == 1 | J5: totalHL == 1 | K5: filter((WS1 %in% c(21,31,41,51,52,91,93) & WS3 == 3) | WS1 %in% c(61,71,72,73)) - - - between(WS4,1,30) | L5: total1 == 1 | M5: totalHL1 == 1
A7: Total | B7: total == 1 | C7: p | H7: 100 | I7: n | J7: n_unw | K7: p | L7: n | M7: n_unw
A9: Area
A10: Urban | B10: area == 1 | H10: 100
A11: Rural | B11: area == 2 | H11: 100
A12: Region
A13: Western | B13: region == 1 | H13: 100
A14: Khangai | B14: region == 2 | H14: 100
A15: Central | B15: region == 3 | H15: 100
A16: Eastern | B16: region == 4 | H16: 100
A17: Ulaanbaatar | B17: region == 5 | H17: 100
A18: Degree of urbanization
A19: City | B19: degubra == 1 | H19: 100
A20: Town & Semi-dense area | B20: degubra == 2 | H20: 100
A21: Rural area | B21: degubra == 3 | H21: 100
A22: Education of household head
A23: Pre-primary or none | B23: headed == 0 | H23: 100
A24: Primary | B24: headed == 1 | H24: 100
A25: Basic (lower secondary) | B25: headed == 2 | H25: 100
A26: Upper secondary | B26: headed == 3 | H26: 100
A27: Vocational | B27: headed == 4 | H27: 100
A28: College, university | B28: headed == 5 | H28: 100
A29: DK / Missing | B29: headed == 8 | H29: 100
A30: Main source of drinking water
A31: Improved sources | B31: WS1 %in% c(11,12,21,31,41,51,52,61,71,72,73,91,93) | H31: 100
A32: Piped water | B32: WS1 %in% c(11,12) | H32: 100
A33: Tube well / Borehole | B33: WS1 == 21 | H33: 100
A34: Protected well or spring | B34: WS1 %in% c(31,41) | H34: 100
A35: Rain or snow water / Ice | B35: WS1 %in% c(51,52) | H35: 100
A36: Water kiosk | B36: WS1 %in% c(72,73) | H36: 100
A37: Tanker truck / Cart with small tank | B37: WS1 %in% c(61,71) | H37: 100
A38: Bottled water | B38: WS1 == 91 | H38: 100
A39: Large bottle / Dispenser refill | B39: WS1 == 93 | H39: 100
A40: Unimproved sources | B40: WS1 %in% c(32,42,81,96) | H40: 100
A41: Unprotected well or spring | B41: WS1 %in% c(32,42) | H41: 100
A42: Surface water | B42: WS1 == 81 | H42: 100
... A44: Missing | B44: WS1 == 99 | H44: 100
A45: Ethnicity of household head
A46: Khalkh | B46: headethnic == 1 | H46: 100
A47: Khazakh, Durvud, Buriad | B47: headethnic == 2 | H47: 100
A48: Other | B48: headethnic == 6 | H48: 100
A49: DK / Missing | B49: headethnic == 8 | H49: 100
A50: Wealth index quintile
A51: Poorest | B51: windex5 == 1 | H51: 100
A52: Second | B52: windex5 == 2 | H52: 100
A53: Middle | B53: windex5 == 3 | H53: 100
A54: Fourth | B54: windex5 == 4 | H54: 100
A55: Richest | B55: windex5 == 5 | H55: 100
A56: na: not applicable

Sheet 6.4
A1: Table 6.4 Availability of sufficient drinking water when needed | I1: IDX
A2: Percentage of household members with drinking water available in sufficient quantities when needed in the last 7 days, Mongolia MICS Plus 2025-26, Wave 1
C3: Percentage using sources with drinking water available in sufficient quantities in the last 7 days | G3: Number of household members
C4: Source of drinking water | F4: Total
C5: Improved | D5: Unimproved | E5: Missing
B6: hh.sav mutate(hhmemwt = hhweightA*HLnum) filter(HH17 %in% c(0,1)) weight by hhmemwt | C6: WS7 == 2 & WS1 %in% c(11,12,21,31,41,51,52,61,71,72,73,91,93) | D6: WS7 == 2 & WS1 %in% c(32,42,81,96) | E6: WS7 == 2 & WS1 == 99 | F6: WS7 == 2 | G6: total == 1 | H6: totalHL == 1
A8: Total | B8: total == 1 | C8: mean | G8: n | H8: n_unw
A10: Area
A11: Urban | B11: area == 1
A12: Rural | B12: area == 2
A13: Region
A14: Western | B14: region == 1
A15: Khangai | B15: region == 2
A16: Central | B16: region == 3
A17: Eastern | B17: region == 4
A18: Ulaanbaatar | B18: region == 5
A19: Degree of urbanization
A20: City | B20: degubra == 1
A21: Town & Semi-dense area | B21: degubra == 2
A22: Rural area | B22: degubra == 3
A23: Education of household head
A24: Pre-primary or none | B24: headed == 0
A25: Primary | B25: headed == 1
A26: Basic (lower secondary) | B26: headed == 2
A27: Upper secondary | B27: headed == 3
A28: Vocational | B28: headed == 4
A29: College, university | B29: headed == 5
A30: DK / Missing | B30: headed == 8
A31: Main source of drinking water
A32: Improved sources | B32: WS1 %in% c(11,12,21,31,41,51,52,61,71,72,73,91,93)
A33: Piped water | B33: WS1 %in% c(11,12)
A34: Tube well / Borehole | B34: WS1 == 21
A35: Protected well or spring | B35: WS1 %in% c(31,41)
A36: Rain or snow water / Ice | B36: WS1 %in% c(51,52)
A37: Water kiosk | B37: WS1 %in% c(72,73)
A38: Tanker truck / Cart with small tank | B38: WS1 %in% c(61,71)
A39: Bottled water | B39: WS1 == 91
A40: Large bottle / Dispenser refill | B40: WS1 == 93
A41: Unimproved sources | B41: WS1 %in% c(32,42,81,96)
A42: Unprotected well or spring | B42: WS1 %in% c(32,42)
A43: Surface water | B43: WS1 == 81
... A45: Missing | B45: WS1 == 99
A46: Ethnicity of household head
A47: Khalkh | B47: headethnic == 1
A48: Khazakh, Durvud, Buriad | B48: headethnic == 2
A49: Other | B49: headethnic == 6
A50: DK / Missing | B50: headethnic == 8
A51: Wealth index quintile
A52: Poorest | B52: windex5 == 1
A53: Second | B53: windex5 == 2
A54: Middle | B54: windex5 == 3
A55: Fourth | B55: windex5 == 4
A56: Richest | B56: windex5 == 5

Sheet 6.5
A1: Table 6.5 Main reason for insufficient drinking water accessability | P1: IDX
A2: Percentage of household members who did not have sufficient drinking water when needed in the last 7 days and percent distribution by main reason for not having sufficient drinking water in the last 7 days, Mongolia MICS Plus 2025-26, Wave 1
C3: Percentage who did not have sufficient drinking water when needed in the last 7 days | D3: Number of household members | F3: Percent distribution by main reason for not having sufficient drinking water in the last 7 days | M3: Total | N3: Number of household members who did not have sufficient drinking water when needed in the last 7 days
F4: Water source not functional | G4: Water source not accessible | H4: Water not available | I4: Water too expensive | J4: Water supply reduced | K4: Other | L4: DK / Missing
B7: hh.sav mutate(hhmemwt = hhweightA*HLnum) filter(HH17 %in% c(0,1)) weight by hhmemwt | C7: WS7 == 1 | D7: total == 1 | E7: totalHL == 1 | F7: filter(WS7 == 1) - - - WS8 == 1 | G7: WS8 == 4 | H7: WS8 == 2 | I7: WS8 == 3 | J7: WS8 == 5 | K7: WS8 == 6 | L7: WS8 >= 8 | M7: 100 | N7: total1 == 1 | O7: totalHL1 == 1
A9: Total | B9: total == 1 | C9: p | D9: n | E9: n_unw | F9: p | M9: 100 | N9: n | O9: n_unw
A11: Area
A12: Urban | B12: area == 1 | M12: 100
A13: Rural | B13: area == 2 | M13: 100
A14: Region
A15: Western | B15: region == 1 | M15: 100
A16: Khangai | B16: region == 2 | M16: 100
A17: Central | B17: region == 3 | M17: 100
A18: Eastern | B18: region == 4 | M18: 100
A19: Ulaanbaatar | B19: region == 5 | M19: 100
A20: Degree of urbanization
A21: City | B21: degubra == 1 | M21: 100
A22: Town & Semi-dense area | B22: degubra == 2 | M22: 100
A23: Rural area | B23: degubra == 3 | M23: 100
A24: Education of household head
A25: Pre-primary or none | B25: headed == 0 | M25: 100
A26: Primary | B26: headed == 1 | M26: 100
A27: Basic (lower secondary) | B27: headed == 2 | M27: 100
A28: Upper secondary | B28: headed == 3 | M28: 100
A29: Vocational | B29: headed == 4 | M29: 100
A30: College, university | B30: headed == 5 | M30: 100
A31: DK / Missing | B31: headed == 8 | M31: 100
A32: Main source of drinking water
A33: Improved sources | B33: WS1 %in% c(11,12,21,31,41,51,52,61,71,72,73,91,93) | M33: 100
A34: Piped water | B34: WS1 %in% c(11,12) | M34: 100
A35: Tube well / Borehole | B35: WS1 == 21 | M35: 100
A36: Protected well or spring | B36: WS1 %in% c(31,41) | M36: 100
A37: Rain or snow water / Ice | B37: WS1 %in% c(51,52) | M37: 100
A38: Water kiosk | B38: WS1 %in% c(72,73) | M38: 100
A39: Tanker truck / Cart with small tank | B39: WS1 %in% c(61,71) | M39: 100
A40: Bottled water | B40: WS1 == 91 | M40: 100
A41: Large bottle / Dispenser refill | B41: WS1 == 93 | M41: 100
A42: Unimproved sources | B42: WS1 %in% c(32,42,81,96) | M42: 100
A43: Unprotected well or spring | B43: WS1 %in% c(32,42) | M43: 100
A44: Surface water | B44: WS1 == 81 | M44: 100
... A46: Missing | B46: WS1 == 99 | M46: 100
A47: Ethnicity of household head
A48: Khalkh | B48: headethnic == 1 | M48: 100
A49: Khazakh, Durvud, Buriad | B49: headethnic == 2 | M49: 100
A50: Other | B50: headethnic == 6 | M50: 100
A51: DK / Missing | B51: headethnic == 8 | M51: 100
A52: Wealth index quintile
A53: Poorest | B53: windex5 == 1 | M53: 100
A54: Second | B54: windex5 == 2 | M54: 100
A55: Middle | B55: windex5 == 3 | M55: 100
A56: Fourth | B56: windex5 == 4 | M56: 100
A57: Richest | B57: windex5 == 5 | M57: 100

Sheet 6.6
A1: Table 6.6 Handwashing facility at home and availability of water and soap to wash hands when needed | M1: IDX
A2: Percent distribution of household members by type of handwashing facility at home, and percentage who did not have sufficient water or soap to wash hands when needed in the last 7 days, Mongolia MICS Plus 2025-26, Wave 1
C3: Percent distribution by type of handwashing facility at home | E3: No handwashing place in in the dwelling, yard, or plot | F3: Other | G3: Missing | H3: Total | I3: Percentage who did not have sufficient water to wash hands when needed in the last 7 days | J3: Percentage who did not have sufficient soap to wash hands when needed in the last 7 days | K3: Number of household members
C4: Fixed facility (sink / tap) | D4: Mobile object (bucket / jug / kettlet)
B5: hh.sav mutate(hhmemwt = hhweightA*HLnum) filter(HH17 %in% c(0,1)) weight by hhmemwt | C5: WS20 %in% c(1,2) | D5: WS20 == 3 | E5: WS20 == 4 | F5: WS20 == 6 | G5: WS20 == 9 | H5: 100 | I5: WS21 == 2 | J5: WS23 == 2 | K5: total == 1 | L5: totalHL == 1
A7: Total | B7: total == 1 | C7: p | H7: 100 | I7: p | K7: n | L7: n_unw
A9: Area
A10: Urban | B10: area == 1 | H10: 100
A11: Rural | B11: area == 2 | H11: 100
A12: Region
A13: Western | B13: region == 1 | H13: 100
A14: Khangai | B14: region == 2 | H14: 100
A15: Central | B15: region == 3 | H15: 100
A16: Eastern | B16: region == 4 | H16: 100
A17: Ulaanbaatar | B17: region == 5 | H17: 100
A18: Degree of urbanization
A19: City | B19: degubra == 1 | H19: 100
A20: Town & Semi-dense area | B20: degubra == 2 | H20: 100
A21: Rural area | B21: degubra == 3 | H21: 100
A22: Education of household head
A23: Pre-primary or none | B23: headed == 0 | H23: 100
A24: Primary | B24: headed == 1 | H24: 100
A25: Basic (lower secondary) | B25: headed == 2 | H25: 100
A26: Upper secondary | B26: headed == 3 | H26: 100
A27: Vocational | B27: headed == 4 | H27: 100
A28: College, university | B28: headed == 5 | H28: 100
A29: DK / Missing | B29: headed == 8 | H29: 100
A30: Ethnicity of household head
A31: Khalkh | B31: headethnic == 1 | H31: 100
A32: Khazakh, Durvud, Buriad | B32: headethnic == 2 | H32: 100
A33: Other | B33: headethnic == 6 | H33: 100
A34: DK / Missing | B34: headethnic == 8 | H34: 100
A35: Wealth index quintile
A36: Poorest | B36: windex5 == 1 | H36: 100
A37: Second | B37: windex5 == 2 | H37: 100
A38: Middle | B38: windex5 == 3 | H38: 100
A39: Fourth | B39: windex5 == 4 | H39: 100
A40: Richest | B40: windex5 == 5 | H40: 100

Sheet 6.6a
A1: Table 6.6a Main reason for insufficient water accessability to wash hands | M1: IDX
A2: Percent distribution of household members who did not have sufficient water to wash hands when needed in the last 7 days by main reason for not having sufficient water to wash hands, Mongolia MICS Plus 2025-26, Wave 1
C3: Percent distribution by main reason for not having sufficient water to wash hands when needed in the last 7 days | J3: Total | K3: Number of household members who did not have sufficient water to wash hands when needed in the last 7 days
C4: Water source not functional | D4: Water source not accessible | E4: Water not available | F4: Water too expensive | G4: Water supply reduced | H4: Other | I4: DK / Missing
B5: hh.sav mutate(hhmemwt = hhweightA*HLnum) filter(HH17 %in% c(0,1) & WS21 == 2) weight by hhmemwt | C5: WS22 == 1 | D5: WS22 == 4 | E5: WS22 == 2 | F5: WS22 == 3 | G5: WS22 == 5 | H5: WS22 == 6 | I5: WS22 >= 8 | J5: 100 | K5: total == 1 | L5: totalHL == 1
A7: Total | B7: total == 1 | C7: p | J7: 100 | K7: n | L7: n_unw
A9: Area
A10: Urban | B10: area == 1 | J10: 100
A11: Rural | B11: area == 2 | J11: 100
A12: Region
A13: Western | B13: region == 1 | J13: 100
A14: Khangai | B14: region == 2 | J14: 100
A15: Central | B15: region == 3 | J15: 100
A16: Eastern | B16: region == 4 | J16: 100
A17: Ulaanbaatar | B17: region == 5 | J17: 100
A18: Degree of urbanization
A19: City | B19: degubra == 1 | J19: 100
A20: Town & Semi-dense area | B20: degubra == 2 | J20: 100
A21: Rural area | B21: degubra == 3 | J21: 100
A22: Education of household head
A23: Pre-primary or none | B23: headed == 0 | J23: 100
A24: Primary | B24: headed == 1 | J24: 100
A25: Basic (lower secondary) | B25: headed == 2 | J25: 100
A26: Upper secondary | B26: headed == 3 | J26: 100
A27: Vocational | B27: headed == 4 | J27: 100
A28: College, university | B28: headed == 5 | J28: 100
A29: DK / Missing | B29: headed == 8 | J29: 100
A30: Ethnicity of household head
A31: Khalkh | B31: headethnic == 1 | J31: 100
A32: Khazakh, Durvud, Buriad | B32: headethnic == 2 | J32: 100
A33: Other | B33: headethnic == 6 | J33: 100
A34: DK / Missing | B34: headethnic == 8 | J34: 100
A35: Wealth index quintile
A36: Poorest | B36: windex5 == 1 | J36: 100
A37: Second | B37: windex5 == 2 | J37: 100
A38: Middle | B38: windex5 == 3 | J38: 100
A39: Fourth | B39: windex5 == 4 | J39: 100
A40: Richest | B40: windex5 == 5 | J40: 100

Sheet 6.6b
A1: Table 6.6b Main reason for insufficient soap accessability to wash hands | J1: IDX
A2: Percent distribution of household members who did not have sufficient soap to wash hands when needed in the last 7 days by main reason for not having sufficient soap to wash hands, Mongolia MICS Plus 2025-26, Wave 1
C3: Percent distribution by main reason for not having sufficient soap to wash hands when needed in the last 7 days | G3: Total | H3: Number of household members who did not have sufficient soap to wash hands when needed in the last 7 days
C4: Soap not available at the market | D4: Soap too expensive | E4: Other | F4: Missing
B5: hh.sav mutate(hhmemwt = hhweightA*HLnum) filter(HH17 %in% c(0,1) & WS23 == 2) weight by hhmemwt | C5: WS24 == 1 | D5: WS24 == 2 | E5: WS24 == 6 | F5: WS24 == 9 | G5: 100 | H5: total == 1 | I5: totalHL == 1
A7: Total | B7: total == 1 | C7: p | G7: 100 | H7: n | I7: n_unw
A9: Area
A10: Urban | B10: area == 1 | G10: 100
A11: Rural | B11: area == 2 | G11: 100
A12: Region
A13: Western | B13: region == 1 | G13: 100
A14: Khangai | B14: region == 2 | G14: 100
A15: Central | B15: region == 3 | G15: 100
A16: Eastern | B16: region == 4 | G16: 100
A17: Ulaanbaatar | B17: region == 5 | G17: 100
A18: Degree of urbanization
A19: City | B19: degubra == 1 | G19: 100
A20: Town & Semi-dense area | B20: degubra == 2 | G20: 100
A21: Rural area | B21: degubra == 3 | G21: 100
A22: Education of household head
A23: Pre-primary or none | B23: headed == 0 | G23: 100
A24: Primary | B24: headed == 1 | G24: 100
A25: Basic (lower secondary) | B25: headed == 2 | G25: 100
A26: Upper secondary | B26: headed == 3 | G26: 100
A27: Vocational | B27: headed == 4 | G27: 100
A28: College, university | B28: headed == 5 | G28: 100
A29: DK / Missing | B29: headed == 8 | G29: 100
A30: Ethnicity of household head
A31: Khalkh | B31: headethnic == 1 | G31: 100
A32: Khazakh, Durvud, Buriad | B32: headethnic == 2 | G32: 100
A33: Other | B33: headethnic == 6 | G33: 100
A34: DK / Missing | B34: headethnic == 8 | G34: 100
A35: Wealth index quintile
A36: Poorest | B36: windex5 == 1 | G36: 100
A37: Second | B37: windex5 == 2 | G37: 100
A38: Middle | B38: windex5 == 3 | G38: 100
A39: Fourth | B39: windex5 == 4 | G39: 100
A40: Richest | B40: windex5 == 5 | G40: 100

Sheet 6.7
A1: Table 6.7 Use of improved and unimproved sanitation facilities | U1: IDX
A2: Percent distribution of household members by type of sanitation facility used by the household and percentage using improved sanitation facilities, Mongolia MICS Plus 2025-26, Wave 1
C3: Percent distribution of household members by type of sanitation facility used by the household | N3: Open defecation (no facility, bush, field) | O3: Missing | P3: Total | Q3: Percentage using improved sanitation facilities | R3: Percentage using improved sanitation facilities (country specific)A | S3: Number of household members
C4: Improved sanitation facility | K4: Unimproved sanitation facility
C5: Flush / Pour flush to: | G5: Ventilated improved pit latrine | H5: Pit latrine with slab | I5: Composting toilet | K5: Open drain | L5: Pit latrine without slab / Open pit | M5: Other
C6: Piped sewer system | D6: Septic tank | E6: Pit latrine / Cesspool | F6: DK where
B7: hh.sav mutate(hhmemwt = hhweightA*HLnum) filter(HH17 %in% c(0,1)) weight by hhmemwt | C7: WS11 == 11 | D7: WS11 == 12 | E7: WS11 == 13 | F7: WS11 == 18 | G7: WS11 == 21 | H7: WS11 == 22 | I7: WS11 == 31 | K7: WS11 == 14 | L7: WS11 == 23 | M7: WS11 == 96 | N7: WS11 == 95 | O7: WS11 == 99 | P7: 100 | Q7: WS11 %in% c(11,12,13,18,21,22,31) | R7: WS11 %in% c(11,12,13,18,21,31) | S7: total == 1 | T7: totalHL == 1
A9: Total | B9: total == 1 | C9: p | P9: 100 | Q9: p | S9: n | T9: n_unw
A11: Area
A12: Urban | B12: area == 1 | P12: 100
A13: Rural | B13: area == 2 | P13: 100
A14: Region
A15: Western | B15: region == 1 | P15: 100
A16: Khangai | B16: region == 2 | P16: 100
A17: Central | B17: region == 3 | P17: 100
A18: Eastern | B18: region == 4 | P18: 100
A19: Ulaanbaatar | B19: region == 5 | P19: 100
A20: Degree of urbanization
A21: City | B21: degubra == 1 | P21: 100
A22: Town & Semi-dense area | B22: degubra == 2 | P22: 100
A23: Rural area | B23: degubra == 3 | P23: 100
A24: Education of household head
A25: Pre-primary or none | B25: headed == 0 | P25: 100
A26: Primary | B26: headed == 1 | P26: 100
A27: Basic (lower secondary) | B27: headed == 2 | P27: 100
A28: Upper secondary | B28: headed == 3 | P28: 100
A29: Vocational | B29: headed == 4 | P29: 100
A30: College, university | B30: headed == 5 | P30: 100
A31: DK / Missing | B31: headed == 8 | P31: 100
A32: Location of sanitation facility
A33: In dwelling | B33: WS14 == 1 | P33: 100
A34: In plot / yard | B34: WS14 == 2 | P34: 100
A35: Elsewhere | B35: WS14 == 3 | P35: 100
A36: No facility / Bush / Field | B36: WS11 == 95 | P36: 100
A37: Missing | B37: WS11 == 99 | WS14 == 9 | P37: 100
A38: Ethnicity of household head
A39: Khalkh | B39: headethnic == 1 | P39: 100
A40: Khazakh, Durvud, Buriad | B40: headethnic == 2 | P40: 100
A41: Other | B41: headethnic == 6 | P41: 100
A42: DK / Missing | B42: headethnic == 8 | P42: 100
A43: Wealth index quintile
A44: Poorest | B44: windex5 == 1 | P44: 100
A45: Second | B45: windex5 == 2 | P45: 100
A46: Middle | B46: windex5 == 3 | P46: 100
A47: Fourth | B47: windex5 == 4 | P47: 100
A48: Richest | B48: windex5 == 5 | P48: 100
A49: A Country specific definition excluded pit latrine with slab from the standard definition

Sheet 6.8
A1: Table 6.8 Use of basic and limited toilet facilities | W1: IDX
A2: Percent distribution of household members by use of private and public sanitation facilities and use of shared facilities, by users of improved and unimproved sanitation facilities and percentage using at least basic sanitation services, Mongolia MICS Plus 2025-26, Wave 1
C3: Percentage using improved toilet facilities that are: | J3: Percentage using unimproved toilet facilities that are: | P3: Open defecation (no facility, bush, field) | Q3: Missing | R3: Total | S3: Percentage using: | U3: Number of household members
C4: Not shared | D4: Shared by | H4: Public facility | K4: Shared by | O4: Public facility | S4: improved sanitation facilities shared with other households | T4: at least basic sanitation services
D5: 5 households or less | E5: More than 5 households | F5: DK how many households | G5: Missing | J5: Not shared | K5: 5 households or less | L5: More than 5 households | M5: DK how many households | N5: Missing
B6: hh.sav mutate(hhmemwt = hhweightA*HLnum) filter(HH17 %in% c(0,1)) weight by hhmemwt | C6: WS11 %in% c(11,12,13,18,21,22,31) & WS15 == 2 | D6: WS11 %in% c(11,12,13,18,21,22,31) & WS17 <= 5 | E6: WS11 %in% c(11,12,13,18,21,22,31) & between(WS17,6,10) | F6: WS11 %in% c(11,12,13,18,21,22,31) & WS17 == 98 | G6: WS11 %in% c(11,12,13,18,21,22,31) & (WS15 == 9 | WS17 == 99) | H6: WS11 %in% c(11,12,13,18,21,22,31) & WS16 == 2 | J6: WS11 %in% c(14,23,96) & WS15 == 2 | K6: WS11 %in% c(14,23,96) & WS17 <= 5 | L6: WS11 %in% c(14,23,96) & between(WS17,6,10) | M6: WS11 %in% c(14,23,96) & WS17 == 98 | N6: WS11 %in% c(14,23,96) & (WS15 == 9 | WS17 == 99) | O6: WS11 %in% c(14,23,96) & WS16 == 2 | P6: WS11 == 95 | Q6: WS11 == 99 | R6: 100 | S6: WS11 %in% c(11,12,13,18,21,22,31) & WS15 == 1 | T6: WS11 %in% c(11,12,13,18,21,22,31) & WS15 == 2 | U6: total == 1 | V6: totalHL == 1
A8: Total | B8: total == 1 | C8: p | R8: 100 | S8: p | U8: n | V8: n_unw
A10: Area
A11: Urban | B11: area == 1 | R11: 100
A12: Rural | B12: area == 2 | R12: 100
A13: Region
A14: Western | B14: region == 1 | R14: 100
A15: Khangai | B15: region == 2 | R15: 100
A16: Central | B16: region == 3 | R16: 100
A17: Eastern | B17: region == 4 | R17: 100
A18: Ulaanbaatar | B18: region == 5 | R18: 100
A19: Degree of urbanization
A20: City | B20: degubra == 1 | R20: 100
A21: Town & Semi-dense area | B21: degubra == 2 | R21: 100
A22: Rural area | B22: degubra == 3 | R22: 100
A23: Education of household head
A24: Pre-primary or none | B24: headed == 0 | R24: 100
A25: Primary | B25: headed == 1 | R25: 100
A26: Basic (lower secondary) | B26: headed == 2 | R26: 100
A27: Upper secondary | B27: headed == 3 | R27: 100
A28: Vocational | B28: headed == 4 | R28: 100
A29: College, university | B29: headed == 5 | R29: 100
A30: DK / Missing | B30: headed == 8 | R30: 100
A31: Type of sanitation facility
A32: Flush to | B32: WS11 %in% c(11,12,13,14,18) | R32: 100
A33: Piped sewer system | B33: WS11 == 11 | R33: 100
A34: Septic tank | B34: WS11 == 12 | R34: 100
A35: Pit latrine / Cesspool | B35: WS11 == 13 | R35: 100
A36: Open drain | B36: WS11 == 14 | R36: 100
A37: DK where | B37: WS11 == 18 | R37: 100
A38: Pit latrine | B38: WS11 %in% c(21,22,23) | R38: 100
A39: Ventilated improved pit latrine | B39: WS11 == 21 | R39: 100
A40: Pit latrine with slab | B40: WS11 == 22 | R40: 100
A41: Pit latrine without slab / Open pit | B41: WS11 == 23 | R41: 100
A42: Composting toilet | B42: WS11 == 31 | R42: 100
A43: Other | B43: WS11 == 96 | R43: 100
... A45: Missing | B45: WS11 == 99 | R45: 100
A46: Location of sanitation facility
A47: In dwelling | B47: WS14 == 1 | R47: 100
A48: In plot / yard | B48: WS14 == 2 | R48: 100
A49: Elsewhere | B49: WS14 == 3 | R49: 100
A50: No facility / Bush / Field | B50: WS11 == 95 | R50: 100
A51: Missing | B51: WS11 == 99 | WS14 == 9 | R51: 100
A52: Ethnicity of household head
A53: Khalkh | B53: headethnic == 1 | R53: 100
A54: Khazakh, Durvud, Buriad | B54: headethnic == 2 | R54: 100
A55: Other | B55: headethnic == 6 | R55: 100
A56: DK / Missing | B56: headethnic == 8 | R56: 100
A57: Wealth index quintile
A58: Poorest | B58: windex5 == 1 | R58: 100
A59: Second | B59: windex5 == 2 | R59: 100
A60: Middle | B60: windex5 == 3 | R60: 100
A61: Fourth | B61: windex5 == 4 | R61: 100
A62: Richest | B62: windex5 == 5 | R62: 100
